Workbook

Sheet Leia-me
B2: Ficha técnica do Maluzices
B3: Esta planilha já vem preenchida com as suas receitas. É para conferir e, daqui para frente, manter.
B5: Como ler as cores
B6: Fundo amarelo e letra azul: campo seu, pode digitar à vontade.
B7: Letra preta: a planilha calcula sozinha. Se você digitar por cima, a conta some.
B8: Letra verde: o valor vem de outra aba.
B9: Linhas de fundo claro no topo dos Insumos: sub-receitas, com preço calculado.
B11: As abas
B12: Insumos: tudo que você compra, com peso bruto, peso líquido e preço.
B13: Produtos: uma linha por receita, com rendimento, preço e os custos calculados.
B14: Ingredientes: o que entra em cada receita e quanto. É daqui que sai o custo.
B15: Conferência: compara estes números com os da sua planilha antiga.
... B44: Alguns ingredientes continuam sem preço porque não existem na lista de insumos com nenhum nome parecido (óleo de girassol, melado de cana, gelo, entre outros). Eles estão listados na aba Pendências. Enquanto não tiverem preço, as receitas que os usam continuam saindo mais baratas do que são.

Sheet Insumos
A1: Insumos
A2: Tudo que entra nas receitas. As linhas amarelas são as que você preenche; as de fundo claro no topo são sub-receitas e têm o preço calculado sozinho.
A3: Código | B3: Nome | C3: Unidade | D3: Peso bruto | E3: Peso líquido | F3: Fator de correção | G3: Preço por quilo | H3: Fornecedor | I3: Data da cotação | J3: Observação
A4: creme-de-castanha | B4: Creme de Castanha | C4: kg | D4: 1 | E4: 1 | F4: =IFERROR(E4/D4,1) -> 1 | G4: =Produtos!$M$17 -> 27.661974 | H4: cozinha | J4: Sub-receita: o preço sai da aba Produtos, não se digita.
A5: creme-para-quiche | B5: Creme para Quiche | C5: kg | D5: 0.5 | E5: 0.5 | F5: =IFERROR(E5/D5,1) -> 1 | G5: =Produtos!$M$40 -> 14.666824 | H5: cozinha | J5: Sub-receita: o preço sai da aba Produtos, não se digita.
A6: frango-desfiado | B6: Frango Desfiado | C6: kg | D6: 1 | E6: 0.5 | F6: =IFERROR(E6/D6,1) -> 0.5 | G6: =Produtos!$M$28 -> 22.902943 | H6: cozinha | J6: Sub-receita: o preço sai da aba Produtos, não se digita.
A7: frango-desfiado-com-molho-de-tomate | B7: Frango Desfiado com Molho de Tomate | C7: kg | D7: 1 | E7: 1 | F7: =IFERROR(E7/D7,1) -> 1 | G7: =Produtos!$M$29 -> 34.885912 | H7: cozinha | J7: Sub-receita: o preço sai da aba Produtos, não se digita.
A8: leite-de-amendoim | B8: Leite de Amendoim | C8: L | D8: 1 | E8: 0.98 | F8: =IFERROR(E8/D8,1) -> 0.98 | G8: =Produtos!$M$33 -> 3.0612245 | H8: cozinha | J8: Sub-receita: o preço sai da aba Produtos, não se digita.
A9: leite-de-arroz | B9: Leite de Arroz | C9: L | D9: 1 | E9: 0.98 | F9: =IFERROR(E9/D9,1) -> 0.98 | G9: =Produtos!$M$34 -> 1.5306122 | H9: cozinha | J9: Sub-receita: o preço sai da aba Produtos, não se digita.
A10: maionese-verde | B10: Maionese Verde | C10: kg | D10: 1 | E10: 1.134 | F10: =IFERROR(E10/D10,1) -> 1.134 | G10: =Produtos!$M$35 -> 6.0598778 | H10: cozinha | J10: Sub-receita: o preço sai da aba Produtos, não se digita.
A11: manteiga-vegana | B11: Manteiga Vegana | C11: kg | D11: 0.8 | E11: 0.8 | F11: =IFERROR(E11/D11,1) -> 1 | G11: =Produtos!$M$37 -> 25.283136 | H11: cozinha | J11: Sub-receita: o preço sai da aba Produtos, não se digita.
A12: massa-low-carb-para-quiche | B12: Massa Low Carb para Quiche | C12: kg | D12: 1 | E12: 1 | F12: =IFERROR(E12/D12,1) -> 1 | G12: =Produtos!$M$39 -> 14.050145 | H12: cozinha | J12: Sub-receita: o preço sai da aba Produtos, não se digita.
A13: massa-de-esfira | B13: Massa de Esfira | C13: kg | D13: 1 | E13: 1 | F13: =IFERROR(E13/D13,1) -> 1 | G13: =Produtos!$M$43 -> 13.987941 | H13: cozinha | J13: Sub-receita: o preço sai da aba Produtos, não se digita.
A14: mix-de-sementes-para-pao | B14: Mix de Sementes para Pão | C14: kg | D14: 1 | E14: 1 | F14: =IFERROR(E14/D14,1) -> 1 | G14: =Produtos!$M$45 -> 45.921939 | H14: cozinha | J14: Sub-receita: o preço sai da aba Produtos, não se digita.
A15: mix-sem-gluten-cris-gutierrez | B15: Mix sem Glúten Cris Gutierrez | C15: kg | D15: 1 | E15: 0.98 | F15: =IFERROR(E15/D15,1) -> 0.98 | G15: =Produtos!$M$47 -> 10.219598 | H15: cozinha | J15: Sub-receita: o preço sai da aba Produtos, não se digita.
A16: pure-de-batatas | B16: Purê de Batatas | C16: kg | D16: 1 | E16: 1 | F16: =IFERROR(E16/D16,1) -> 1 | G16: =Produtos!$M$54 -> 12.142728 | H16: cozinha | J16: Sub-receita: o preço sai da aba Produtos, não se digita.
A17: pao-roberta | B17: Pão Roberta | C17: kg | D17: 1 | E17: 0.98 | F17: =IFERROR(E17/D17,1) -> 0.98 | G17: =Produtos!$M$56 -> 9.3401927 | H17: cozinha | J17: Sub-receita: o preço sai da aba Produtos, não se digita.
A18: pao-nobis | B18: Pão-nóbis | C18: kg | D18: 1 | E18: 1 | F18: =IFERROR(E18/D18,1) -> 1 | G18: =Produtos!$M$64 -> 11.85252 | H18: cozinha | J18: Sub-receita: o preço sai da aba Produtos, não se digita.
A19: requeiju | B19: Requeiju | C19: kg | D19: 1 | E19: 1.18 | F19: =IFERROR(E19/D19,1) -> 1.18 | G19: =Produtos!$M$70 -> 16.769479 | H19: cozinha | J19: Sub-receita: o preço sai da aba Produtos, não se digita.
A20: abacaxi-sem-casca | B20: Abacaxi sem Casca | C20: kg | D20: 1 | E20: 0.63 | F20: =IFERROR(E20/D20,1) -> 0.63 | G20: 4 | H20: Cantina
A21: abobora-cabotia | B21: Abobora Cabotia | C21: kg | D21: 1 | E21: 0.97 | F21: =IFERROR(E21/D21,1) -> 0.97 | G21: 6
A22: abobrinha-crua | B22: Abobrinha Crua | C22: kg | D22: 1 | E22: 0.95 | F22: =IFERROR(E22/D22,1) -> 0.95 | G22: 2.49
A23: alecrim | B23: Alecrim | C23: kg | D23: 1 | E23: 0.95 | F23: =IFERROR(E23/D23,1) -> 0.95 | G23: 10
A24: alface | B24: Alface | C24: kg | D24: 1 | E24: 0.79 | F24: =IFERROR(E24/D24,1) -> 0.79 | G24: 5
A25: alho-cru | B25: Alho Cru | C25: kg | D25: 1 | E25: 0.88 | F25: =IFERROR(E25/D25,1) -> 0.88 | G25: 24.99
A26: alho-descascado | B26: Alho Descascado | C26: kg | D26: 1 | E26: 0.88 | F26: =IFERROR(E26/D26,1) -> 0.88 | G26: 20
A27: alho-poro | B27: Alho-poró | C27: kg | D27: 1 | E27: 0.9 | F27: =IFERROR(E27/D27,1) -> 0.9 | G27: 50 | H27: Feirinha
A28: amaranto-em-flocos | B28: Amaranto em Flocos | C28: kg | D28: 1 | E28: 0.98 | F28: =IFERROR(E28/D28,1) -> 0.98 | G28: 23 | H28: Ares
A29: amendoas-em-castanha | B29: Amendoas em Castanha | C29: kg | D29: 1 | E29: 0.9 | F29: =IFERROR(E29/D29,1) -> 0.9 | G29: 62 | H29: Ares
A30: amendoim | B30: Amendoim | C30: kg | D30: 1 | E30: 0.98 | F30: =IFERROR(E30/D30,1) -> 0.98 | G30: 5.3 | H30: Cedro
A31: amido-de-milho | B31: Amido de Milho | C31: kg | D31: 0.5 | E31: 0.49 | F31: =IFERROR(E31/D31,1) -> 0.98 | G31: 4
A32: aveia | B32: Aveia | C32: kg | D32: 1 | E32: 0.98 | F32: =IFERROR(E32/D32,1) -> 0.98 | G32: 16.9
A33: aveia-em-flocos-grossos | B33: Aveia em Flocos Grossos | C33: kg | D33: 1 | E33: 0.98 | F33: =IFERROR(E33/D33,1) -> 0.98 | G33: 18.26
A34: avela-torrada | B34: Avelã Torrada | C34: kg | D34: 1 | E34: 0.88 | F34: =IFERROR(E34/D34,1) -> 0.88 | G34: 90 | H34: Ares da Natureza
A35: azeite-de-oliva | B35: Azeite de Oliva | C35: kg | D35: 1 | E35: 0.95 | F35: =IFERROR(E35/D35,1) -> 0.95 | G35: 20 | H35: Argentina
A36: acucar-demerara | B36: Açucar Demerara | C36: kg | D36: 1 | E36: 0.98 | F36: =IFERROR(E36/D36,1) -> 0.98 | G36: 6 | H36: Cedro
A37: acucar-mascavo | B37: Açúcar Mascavo | C37: kg | D37: 1 | E37: 0.98 | F37: =IFERROR(E37/D37,1) -> 0.98 | G37: 9 | H37: Equi
A38: acucar-de-coco | B38: Açúcar de Coco | C38: kg | D38: 1 | E38: 0.97 | F38: =IFERROR(E38/D38,1) -> 0.97 | G38: 26.2 | H38: Ares
A39: banana-com-casca | B39: Banana com Casca | C39: kg | D39: 1 | E39: 0.95 | F39: =IFERROR(E39/D39,1) -> 0.95 | G39: 6
A40: banana-sem-casca | B40: Banana sem Casca | C40: kg | D40: 1 | E40: 0.62 | F40: =IFERROR(E40/D40,1) -> 0.62 | G40: 10 | H40: Cantina da Fruta
A41: batata-asterix | B41: Batata Asterix | C41: kg | D41: 1 | E41: 0.85 | F41: =IFERROR(E41/D41,1) -> 0.85 | G41: 8
A42: batata-doce-cozida-no-vapor | B42: Batata Doce Cozida No Vapor | C42: kg | D42: 2.039 | E42: 1.917 | F42: =IFERROR(E42/D42,1) -> 0.94016675 | G42: 12
A43: batata-doce-crua-sem-casca | B43: Batata Doce Crua sem Casca | C43: kg | D43: 2.367 | E43: 2.039 | F43: =IFERROR(E43/D43,1) -> 0.86142797 | G43: 5.69
A44: batata-monalisa-in-natura | B44: Batata Monalisa In Natura | C44: kg | D44: 1 | E44: 0.8 | F44: =IFERROR(E44/D44,1) -> 0.8 | G44: 6
A45: baunilha-em-pasta | B45: Baunilha em Pasta | C45: kg | D45: 0.2 | E45: 0.198 | F45: =IFERROR(E45/D45,1) -> 0.99 | G45: 42
A46: beterraba | B46: Beterraba | C46: kg | D46: 1 | E46: 0.9 | F46: =IFERROR(E46/D46,1) -> 0.9 | G46: 5
A47: beterraba-em-po | B47: Beterraba em Pó | C47: kg | D47: 1 | E47: 0.95 | F47: =IFERROR(E47/D47,1) -> 0.95 | G47: 63.52
A48: bicarbonato-se-sodio | B48: Bicarbonato Se Sódio | C48: kg | D48: 1 | E48: 0.98 | F48: =IFERROR(E48/D48,1) -> 0.98 | G48: 5.44 | H48: Organicos e Cia
A49: brocolis | B49: Brócolis | C49: kg | D49: 1 | E49: 0.95 | F49: =IFERROR(E49/D49,1) -> 0.95 | G49: 30 | H49: Fruteira
A50: cacau-em-po | B50: Cacau em Pó | C50: kg | D50: 1 | E50: 0.98 | F50: =IFERROR(E50/D50,1) -> 0.98 | G50: 67.5 | H50: Equilibrium
A51: cafe-soluvel | B51: Café Solúvel | C51: kg | D51: 1 | E51: 0.9 | F51: =IFERROR(E51/D51,1) -> 0.9 | G51: 200 | H51: Cacau Show
A52: caldo-de-frango | B52: Caldo de Frango | C52: kg | D52: 1 | E52: 0.98 | F52: =IFERROR(E52/D52,1) -> 0.98 | G52: 10
A53: canela-em-po | B53: Canela em Pó | C53: kg | D53: 1 | E53: 0.98 | F53: =IFERROR(E53/D53,1) -> 0.98 | G53: 27 | H53: Ares
A54: carne-moida | B54: Carne Moida | C54: kg | D54: 1 | E54: 0.95 | F54: =IFERROR(E54/D54,1) -> 0.95 | G54: 60
A55: castanha-de-caju | B55: Castanha de Caju | C55: kg | D55: 1 | E55: 0.98 | F55: =IFERROR(E55/D55,1) -> 0.98 | G55: 69.9 | H55: Ares da Natureza
A56: castanha-do-para-inteira | B56: Castanha do Pará Inteira | C56: kg | D56: 1 | E56: 0.95 | F56: =IFERROR(E56/D56,1) -> 0.95 | G56: 94.9 | H56: Equilibrium
A57: cebola-sem-casca | B57: Cebola sem Casca | C57: kg | D57: 1 | E57: 0.84 | F57: =IFERROR(E57/D57,1) -> 0.84 | G57: 6
A58: cenoura-com-casca | B58: Cenoura com Casca | C58: kg | D58: 1 | E58: 0.98 | F58: =IFERROR(E58/D58,1) -> 0.98 | G58: 7.9
A59: chia | B59: Chia | C59: kg | D59: 1 | E59: 0.98 | F59: =IFERROR(E59/D59,1) -> 0.98 | G59: 34.89 | H59: Ares
A60: chocolate-80-ares | B60: Chocolate 80% Ares | C60: kg | D60: 1 | E60: 0.98 | F60: =IFERROR(E60/D60,1) -> 0.98 | G60: 55
A61: chocolate-branco-divine-vegano-zero-acuc | B61: Chocolate Branco Divine Vegano Zero Açúcar | C61: kg | D61: 1 | E61: 0.95 | F61: =IFERROR(E61/D61,1) -> 0.95 | G61: 70 | H61: Ares
A62: chocolate-planalto-70 | B62: Chocolate Planalto 70% | C62: kg | D62: 1 | E62: 0.98 | F62: =IFERROR(E62/D62,1) -> 0.98 | G62: 64 | H62: Ares
A63: chocolate-sicao-branco | B63: Chocolate Sicao Branco | C63: kg | D63: 1 | E63: 0.95 | F63: =IFERROR(E63/D63,1) -> 0.95 | G63: 33
A64: chocolate-sicao-meio-amargo | B64: Chocolate Sicao Meio Amargo | C64: kg | D64: 1 | E64: 0.95 | F64: =IFERROR(E64/D64,1) -> 0.95 | G64: 34.5
A65: chuchu | B65: Chuchu | C65: kg | D65: 1 | E65: 0.95 | F65: =IFERROR(E65/D65,1) -> 0.95 | G65: 7
A66: coco-em-flocos-grandes-torrado | B66: Coco em Flocos Grandes Torrado | C66: kg | D66: 1 | E66: 0.98 | F66: =IFERROR(E66/D66,1) -> 0.98 | G66: 38.9
A67: coco-em-flocos-sem-acucar | B67: Coco em Flocos sem Açúcar | C67: kg | D67: 1 | E67: 0.98 | F67: =IFERROR(E67/D67,1) -> 0.98 | G67: 33.9
A68: couve-flor-cozida | B68: Couve-flor Cozida | C68: kg | D68: 1 | E68: 0.98 | F68: =IFERROR(E68/D68,1) -> 0.98 | G68: 10
A69: coxao-mole | B69: Coxão Mole | C69: kg | D69: 1 | E69: 0.85 | F69: =IFERROR(E69/D69,1) -> 0.85 | G69: 53
A70: creme-pata-quiche-vegan | B70: Creme Pata Quiche Vegan | C70: kg | D70: 1 | E70: 0.95 | F70: =IFERROR(E70/D70,1) -> 0.95 | G70: 17.2616
A71: creme-patissiere | B71: Creme Patissiere | C71: kg | D71: 1 | E71: 0.83 | F71: =IFERROR(E71/D71,1) -> 0.83 | G71: 13.7
A72: cremor-de-tartaro | B72: Cremor de Tártaro | C72: kg | D72: 1 | E72: 0.98 | F72: =IFERROR(E72/D72,1) -> 0.98 | G72: 120
A73: cumaru | B73: Cumaru | C73: kg | D73: 0.015 | E73: 0.015 | F73: =IFERROR(E73/D73,1) -> 1 | G73: 105.8 | H73: Cipra
A74: curcuma-em-po | B74: Curcuma em Pó | C74: kg | D74: 1 | E74: 0.98 | F74: =IFERROR(E74/D74,1) -> 0.98 | G74: 11 | H74: Ares
A75: curry | B75: Curry | C75: kg | D75: 1 | E75: 0.98 | F75: =IFERROR(E75/D75,1) -> 0.98 | G75: 9.54 | H75: Equilibrium
A76: farinha-de-amendoas | B76: Farinha de Amêndoas | C76: kg | D76: 1 | E76: 0.98 | F76: =IFERROR(E76/D76,1) -> 0.98 | G76: 65 | H76: Equi
A77: farinha-de-arroz | B77: Farinha de Arroz | C77: kg | D77: 1 | E77: 0.98 | F77: =IFERROR(E77/D77,1) -> 0.98 | G77: 7.49 | H77: Equi
A78: farinha-de-arroz-integral | B78: Farinha de Arroz Integral | C78: kg | D78: 1 | E78: 0.98 | F78: =IFERROR(E78/D78,1) -> 0.98 | G78: 9.5
A79: farinha-de-coco | B79: Farinha de Coco | C79: kg | D79: 1 | E79: 0.98 | F79: =IFERROR(E79/D79,1) -> 0.98 | G79: 22.5 | H79: Equi
A80: farinha-de-grao-de-bico | B80: Farinha de Grão-de-bico | C80: kg | D80: 1 | E80: 0.98 | F80: =IFERROR(E80/D80,1) -> 0.98 | G80: 36.8
A81: farinha-de-trigo-integral | B81: Farinha de Trigo Integral | C81: kg | D81: 1 | E81: 0.98 | F81: =IFERROR(E81/D81,1) -> 0.98 | G81: 4
A82: feijao-azuki | B82: Feijão Azuki | C82: kg | D82: 1 | E82: 0.98 | F82: =IFERROR(E82/D82,1) -> 0.98 | G82: 11.8 | H82: Ares
A83: feijao-fradinho | B83: Feijão Fradinho | C83: kg | D83: 1 | E83: 1 | F83: =IFERROR(E83/D83,1) -> 1 | G83: 8.9 | H83: Oraganicos e Cia Beltrao
A84: fermento-biologico-seco | B84: Fermento Biologico Seco | C84: kg | D84: 1 | E84: 0.98 | F84: =IFERROR(E84/D84,1) -> 0.98 | G84: 14.9 | H84: Marcon Atacado Beltrao
A85: fermento-quimico | B85: Fermento Químico | C85: kg | D85: 1 | E85: 0.98 | F85: =IFERROR(E85/D85,1) -> 0.98 | G85: 55.96 | H85: Cedro
A86: flor-de-sal | B86: Flor de Sal | C86: kg | D86: 1 | E86: 0.98 | F86: =IFERROR(E86/D86,1) -> 0.98 | G86: 45
A87: frango-cru | B87: Frango Cru | C87: kg | D87: 1 | E87: 0.98 | F87: =IFERROR(E87/D87,1) -> 0.98 | G87: 16 | H87: Rafa
A88: fuba-fino | B88: Fubá Fino | C88: kg | D88: 1 | E88: 0.98 | F88: =IFERROR(E88/D88,1) -> 0.98 | G88: 2.89 | H88: Cedro
A89: fecula-de-batata | B89: Fécula de Batata | C89: kg | D89: 1 | E89: 0.98 | F89: =IFERROR(E89/D89,1) -> 0.98 | G89: 15 | H89: Equi
A90: ganache-70-com-leite-de-coco | B90: Ganache 70 com Leite de Coco | C90: kg | D90: 0.3 | E90: 0.29 | F90: =IFERROR(E90/D90,1) -> 0.96666667 | G90: 8
A91: geleia-de-amoras-silvestres | B91: Geleia de Amoras Silvestres | C91: kg | D91: 1 | E91: 0.47 | F91: =IFERROR(E91/D91,1) -> 0.47 | G91: 15
A92: geleia-de-morando | B92: Geleia de Morando | C92: kg | D92: 1 | E92: 0.53 | F92: =IFERROR(E92/D92,1) -> 0.53 | G92: 7.45
A93: gengibre-cru | B93: Gengibre Cru | C93: kg | D93: 1 | E93: 0.95 | F93: =IFERROR(E93/D93,1) -> 0.95 | G93: 19.99
A94: gergelim-branco | B94: Gergelim Branco | C94: kg | D94: 1 | E94: 0.98 | F94: =IFERROR(E94/D94,1) -> 0.98 | G94: 48.85 | H94: Ares
A95: gergelim-preto | B95: Gergelim Preto | C95: kg | D95: 1 | E95: 0.98 | F95: =IFERROR(E95/D95,1) -> 0.98 | G95: 41.42 | H95: Ares
A96: goiabada-cascao | B96: Goiabada Cascão | C96: kg | D96: 1 | E96: 0.95 | F96: =IFERROR(E96/D96,1) -> 0.95 | G96: 6.3 | H96: Marcon Atadaco Beltrao
A97: goma-agar | B97: Goma Agar | C97: kg | D97: 1 | E97: 0.95 | F97: =IFERROR(E97/D97,1) -> 0.95 | G97: 69
A98: goma-xantana | B98: Goma Xantana | C98: kg | D98: 1 | E98: 0.98 | F98: =IFERROR(E98/D98,1) -> 0.98 | G98: 36.86
A99: gorgonzola | B99: Gorgonzola | C99: kg | D99: 1 | E99: 0.95 | F99: =IFERROR(E99/D99,1) -> 0.95 | G99: 40
A100: grao-de-bico-cozido | B100: Grão de Bico Cozido | C100: kg | D100: 1 | E100: 0.98 | F100: =IFERROR(E100/D100,1) -> 0.98 | G100: 15 | H100: Ares
...

Sheet Produtos
A1: Produtos e receitas
A2: Um por linha. Os 12 primeiros são os que você vende; os de baixo são bases e sub-receitas que entram em outras fichas.
A3: Código | B3: Nome | C3: Categoria | D3: Rendimento (porções) | E3: Rendimento (kg) | F3: Tempo de preparo | G3: Vende? | H3: Preço praticado | I3: Meta de CMV | J3: Custo da receita | K3: Custo por porção | L3: Preço sugerido | M3: Custo por quilo | N3: CMV real | O3: Custo na planilha antiga | P3: Diferença
A4: caldo-de-batata-doce | B4: Caldo de Batata Doce | C4: Caldos | D4: 9 | F4: 10 min | G4: Sim | H4: 18 | I4: 0.3 | J4: =SUM(Ingredientes!$I$4:$I$10) -> 48.493647 | K4: =IFERROR(J4/D4,0) -> 5.388183 | L4: =IFERROR(K4/I4,0) -> 17.96061 | M4: =IFERROR(J4/IF(E4>0,E4,SUM(Ingredientes!$E$4:$E$10)),0) -> 13.895028 | N4: =IFERROR(K4/H4,0) -> 0.2993435 | O4: 5.3232 | P4: =IFERROR(K4-O4,0) -> 0.06498298
A5: caldo-de-cabotia | B5: Caldo de Cabotia | C5: Caldos | D5: 9 | F5: 10 min | G5: Sim | H5: 18 | I5: 0.3 | J5: =SUM(Ingredientes!$I$11:$I$17) -> 48.073902 | K5: =IFERROR(J5/D5,0) -> 5.3415447 | L5: =IFERROR(K5/I5,0) -> 17.805149 | M5: =IFERROR(J5/IF(E5>0,E5,SUM(Ingredientes!$E$11:$E$17)),0) -> 13.774757 | N5: =IFERROR(K5/H5,0) -> 0.29675248 | O5: 5.2765 | P5: =IFERROR(K5-O5,0) -> 0.065044711
A6: caldo-de-legumes-e-frango | B6: Caldo de Legumes e Frango | C6: Caldos | D6: 9 | F6: 10 min | G6: Sim | H6: 18 | I6: 0.34 | J6: =SUM(Ingredientes!$I$18:$I$27) -> 55.515484 | K6: =IFERROR(J6/D6,0) -> 6.1683871 | L6: =IFERROR(K6/I6,0) -> 18.142315 | M6: =IFERROR(J6/IF(E6>0,E6,SUM(Ingredientes!$E$18:$E$27)),0) -> 15.907015 | N6: =IFERROR(K6/H6,0) -> 0.34268817 | O6: 6.1034 | P6: =IFERROR(K6-O6,0) -> 0.064987069
A7: coxinha-de-batata-doce | B7: Coxinha Massa Trad | C7: Salgados fritos | D7: 19 | F7: 1H | G7: Sim | H7: 20 | I7: 0.17 | J7: =SUM(Ingredientes!$I$28:$I$32) -> 68.587563 | K7: =IFERROR(J7/D7,0) -> 3.6098718 | L7: =IFERROR(K7/I7,0) -> 21.23454 | M7: =IFERROR(J7/IF(E7>0,E7,SUM(Ingredientes!$E$28:$E$32)),0) -> 19.380493 | N7: =IFERROR(K7/H7,0) -> 0.18049359 | O7: 3.5749 | P7: =IFERROR(K7-O7,0) -> 0.034971762
A8: cracker-sem-gluten | B8: Cracker sem Glúten | C8: Salgados assados | D8: 3 | F8: 1H | G8: Sim | H8: 12 | I8: 0.2 | J8: =SUM(Ingredientes!$I$33:$I$45) -> 7.3380005 | K8: =IFERROR(J8/D8,0) -> 2.4460002 | L8: =IFERROR(K8/I8,0) -> 12.230001 | M8: =IFERROR(J8/IF(E8>0,E8,SUM(Ingredientes!$E$33:$E$45)),0) -> 14.690692 | N8: =IFERROR(K8/H8,0) -> 0.20383335 | O8: 2.446 | P8: =IFERROR(K8-O8,0) -> 1.7901898e-07
A9: esfira-de-carne | B9: Esfira de Carne | C9: Salgados assados | D9: 15 | F9: 10 min | G9: Sim | H9: 18 | I9: 0.35 | J9: =SUM(Ingredientes!$I$46:$I$47) -> 91.0236 | K9: =IFERROR(J9/D9,0) -> 6.06824 | L9: =IFERROR(K9/I9,0) -> 17.337829 | M9: =IFERROR(J9/IF(E9>0,E9,SUM(Ingredientes!$E$46:$E$47)),0) -> 35.556094 | N9: =IFERROR(K9/H9,0) -> 0.33712444 | O9: 6.1932 | P9: =IFERROR(K9-O9,0) -> -0.12496
A10: massa-mini-pizza | B10: Massa Mini Pizza | C10: Massas e bases | D10: 9 | F10: 1H | G10: Sim | H10: 3 | I10: 0.2 | J10: =SUM(Ingredientes!$I$48:$I$56) -> 5.3233049 | K10: =IFERROR(J10/D10,0) -> 0.59147832 | L10: =IFERROR(K10/I10,0) -> 2.9573916 | M10: =IFERROR(J10/IF(E10>0,E10,SUM(Ingredientes!$E$48:$E$56)),0) -> 13.476721 | N10: =IFERROR(K10/H10,0) -> 0.19715944 | O10: 0.5915 | P10: =IFERROR(K10-O10,0) -> -2.1679198e-05
A11: pao-de-mandioquinha | B11: Pão de Mandioquinha | C11: Pães | D11: 16 | F11: 2HR | G11: Sim | H11: 12 | I11: 0.17 | J11: =SUM(Ingredientes!$I$57:$I$64) -> 30.993036 | K11: =IFERROR(J11/D11,0) -> 1.9370648 | L11: =IFERROR(K11/I11,0) -> 11.394499 | M11: =IFERROR(J11/IF(E11>0,E11,SUM(Ingredientes!$E$57:$E$64)),0) -> 12.738609 | N11: =IFERROR(K11/H11,0) -> 0.16142206 | O11: 1.9371 | P11: =IFERROR(K11-O11,0) -> -3.5239885e-05
A12: quiche-de-brocolis | B12: Quiche de Brócolis | C12: Salgados assados | D12: 10 | F12: 10 min | G12: Sim | H12: 17 | I12: 0.24 | J12: =SUM(Ingredientes!$I$65:$I$68) -> 40.620223 | K12: =IFERROR(J12/D12,0) -> 4.0620223 | L12: =IFERROR(K12/I12,0) -> 16.925093 | M12: =IFERROR(J12/IF(E12>0,E12,SUM(Ingredientes!$E$65:$E$68)),0) -> 25.38764 | N12: =IFERROR(K12/H12,0) -> 0.23894249 | O12: 3.9601 | P12: =IFERROR(K12-O12,0) -> 0.10192233
A13: quiche-de-frango | B13: Quiche de Frango | C13: Salgados assados | D13: 10 | F13: 10 min | G13: Sim | H13: 17 | I13: 0.24 | J13: =SUM(Ingredientes!$I$69:$I$72) -> 39.214652 | K13: =IFERROR(J13/D13,0) -> 3.9214652 | L13: =IFERROR(K13/I13,0) -> 16.339438 | M13: =IFERROR(J13/IF(E13>0,E13,SUM(Ingredientes!$E$69:$E$72)),0) -> 24.509157 | N13: =IFERROR(K13/H13,0) -> 0.23067442 | O13: 3.923 | P13: =IFERROR(K13-O13,0) -> -0.0015348205
A14: sanduba-de-frango | B14: Sanduba de Pao-nobis, Frango e Requeiju | C14: Pães | D14: 1 | F14: MODO DE PREPARO | G14: Sim | H14: 17 | I14: 0.2 | J14: =SUM(Ingredientes!$I$73:$I$77) -> 3.3499976 | K14: =IFERROR(J14/D14,0) -> 3.3499976 | L14: =IFERROR(K14/I14,0) -> 16.749988 | M14: =IFERROR(J14/IF(E14>0,E14,SUM(Ingredientes!$E$73:$E$77)),0) -> 3.0593585 | N14: =IFERROR(K14/H14,0) -> 0.19705868 | O14: 3.3114 | P14: =IFERROR(K14-O14,0) -> 0.038597595
A15: torta-salgada-de-frango | B15: Torta Salgada de Frango | C15: Salgados assados | D15: 7 | F15: 40 min | G15: Sim | H15: 15 | I15: 0.2 | J15: =SUM(Ingredientes!$I$78:$I$85) -> 20.486057 | K15: =IFERROR(J15/D15,0) -> 2.9265796 | L15: =IFERROR(K15/I15,0) -> 14.632898 | M15: =IFERROR(J15/IF(E15>0,E15,SUM(Ingredientes!$E$78:$E$85)),0) -> 19.698132 | N15: =IFERROR(K15/H15,0) -> 0.19510531 | O15: 2.8823 | P15: =IFERROR(K15-O15,0) -> 0.044279608
A16: batida-nuts | B16: Batida de Nuts | C16: Bebidas | D16: 1 | F16: 5 min | G16: Não | J16: =SUM(Ingredientes!$I$86:$I$90) -> 2.3583114 | K16: =IFERROR(J16/D16,0) -> 2.3583114 | L16: =IFERROR(K16/I16,0) -> 0 | M16: =IFERROR(J16/IF(E16>0,E16,SUM(Ingredientes!$E$86:$E$90)),0) -> 10.435006 | N16: =IFERROR(K16/H16,0) -> 0 | O16: 2.3583 | P16: =IFERROR(K16-O16,0) -> 1.1389072e-05
A17: creme-de-castanha | B17: Catupiry de Castanha | C17: Caldos | D17: 1 | E17: 0.6217 | F17: 10 min | G17: Não | J17: =SUM(Ingredientes!$I$91:$I$94) -> 17.197449 | K17: =IFERROR(J17/D17,0) -> 17.197449 | L17: =IFERROR(K17/I17,0) -> 0 | M17: =IFERROR(J17/IF(E17>0,E17,SUM(Ingredientes!$E$91:$E$94)),0) -> 27.661974 | N17: =IFERROR(K17/H17,0) -> 0 | O17: 17.1974 | P17: =IFERROR(K17-O17,0) -> 4.8979592e-05
A18: coxinha-de-festa | B18: Coxinha de Festa | C18: Salgados fritos | D18: 25 | F18: 40 min | G18: Não | J18: =SUM(Ingredientes!$I$95:$I$99) -> 9.5413412 | K18: =IFERROR(J18/D18,0) -> 0.38165365 | L18: =IFERROR(K18/I18,0) -> 0 | M18: =IFERROR(J18/IF(E18>0,E18,SUM(Ingredientes!$E$95:$E$99)),0) -> 11.495592 | N18: =IFERROR(K18/H18,0) -> 0 | O18: 0.3827 | P18: =IFERROR(K18-O18,0) -> -0.0010463523
A19: croquete-de-batata-e-frango | B19: Croquete de Batata e Frango | C19: Salgados fritos | D19: 10 | F19: 1H | G19: Não | J19: =SUM(Ingredientes!$I$100:$I$107) -> 31.517018 | K19: =IFERROR(J19/D19,0) -> 3.1517018 | L19: =IFERROR(K19/I19,0) -> 0 | M19: =IFERROR(J19/IF(E19>0,E19,SUM(Ingredientes!$E$100:$E$107)),0) -> 21.947784 | N19: =IFERROR(K19/H19,0) -> 0 | O19: 3.0867 | P19: =IFERROR(K19-O19,0) -> 0.065001816
A20: croquete-de-carne-e-cabotia | B20: Croquete de Batata e Frango | C20: Salgados fritos | D20: 47 | F20: 1H | G20: Não | J20: =SUM(Ingredientes!$I$108:$I$117) -> 45.86076 | K20: =IFERROR(J20/D20,0) -> 0.97576086 | L20: =IFERROR(K20/I20,0) -> 0 | M20: =IFERROR(J20/IF(E20>0,E20,SUM(Ingredientes!$E$108:$E$117)),0) -> 35.386389 | N20: =IFERROR(K20/H20,0) -> 0 | O20: 0.9758 | P20: =IFERROR(K20-O20,0) -> -3.9143761e-05
A21: empada-de-frango | B21: Empada de Frango | C21: Salgados assados | D21: 1 | F21: 10 min | G21: Não | J21: =SUM(Ingredientes!$I$118:$I$119) -> 1.9486759 | K21: =IFERROR(J21/D21,0) -> 1.9486759 | L21: =IFERROR(K21/I21,0) -> 0 | M21: =IFERROR(J21/IF(E21>0,E21,SUM(Ingredientes!$E$118:$E$119)),0) -> 32.477932 | N21: =IFERROR(K21/H21,0) -> 0 | O21: 1.36 | P21: =IFERROR(K21-O21,0) -> 0.58867594
A22: empadinha-veg | B22: Empadinha Veg | C22: Salgados assados | D22: 1 | F22: 1H | G22: Não | J22: =SUM(Ingredientes!$I$120:$I$121) -> 0.42311712 | K22: =IFERROR(J22/D22,0) -> 0.42311712 | L22: =IFERROR(K22/I22,0) -> 0 | M22: =IFERROR(J22/IF(E22>0,E22,SUM(Ingredientes!$E$120:$E$121)),0) -> 14.103904 | N22: =IFERROR(K22/H22,0) -> 0 | O22: 0.1421 | P22: =IFERROR(K22-O22,0) -> 0.28101712
A23: empadinha-de-carne | B23: Empadinha de Carne | C23: Salgados assados | D23: 25 | F23: 40 min | G23: Não | J23: =SUM(Ingredientes!$I$122:$I$123) -> 22.168418 | K23: =IFERROR(J23/D23,0) -> 0.88673673 | L23: =IFERROR(K23/I23,0) -> 0 | M23: =IFERROR(J23/IF(E23>0,E23,SUM(Ingredientes!$E$122:$E$123)),0) -> 29.557891 | N23: =IFERROR(K23/H23,0) -> 0 | O23: 0.899 | P23: =IFERROR(K23-O23,0) -> -0.012263265
A24: empadinha-de-frango | B24: Empadinha de Frango | C24: Salgados assados | D24: 25 | F24: 40 min | G24: Não | J24: =SUM(Ingredientes!$I$124:$I$125) -> 15.889896 | K24: =IFERROR(J24/D24,0) -> 0.63559585 | L24: =IFERROR(K24/I24,0) -> 0 | M24: =IFERROR(J24/IF(E24>0,E24,SUM(Ingredientes!$E$124:$E$125)),0) -> 21.186528 | N24: =IFERROR(K24/H24,0) -> 0 | O24: 0.6267 | P24: =IFERROR(K24-O24,0) -> 0.0088958509
A25: escondidinho-de-carne | B25: Escondidinho de Carne | C25: Outros | D25: 10 | F25: 10 min | G25: Não | J25: =SUM(Ingredientes!$I$126:$I$128) -> 122.04508 | K25: =IFERROR(J25/D25,0) -> 12.204508 | L25: =IFERROR(K25/I25,0) -> 0 | M25: =IFERROR(J25/IF(E25>0,E25,SUM(Ingredientes!$E$126:$E$128)),0) -> 34.870023 | N25: =IFERROR(K25/H25,0) -> 0 | O25: 12.4247 | P25: =IFERROR(K25-O25,0) -> -0.22019212
A26: escondidinho-de-frango | B26: Escondidinho de Carne | C26: Outros | D26: 10 | F26: 10 min | G26: Não | J26: =SUM(Ingredientes!$I$129:$I$131) -> 84.373946 | K26: =IFERROR(J26/D26,0) -> 8.4373946 | L26: =IFERROR(K26/I26,0) -> 0 | M26: =IFERROR(J26/IF(E26>0,E26,SUM(Ingredientes!$E$129:$E$131)),0) -> 24.106842 | N26: =IFERROR(K26/H26,0) -> 0 | O26: 8.3411 | P26: =IFERROR(K26-O26,0) -> 0.096294618
A27: focacciaa | B27: Focaccia de Tomate e Alecrim | C27: Pães | D27: 1 | F27: 1H | G27: Não | J27: =SUM(Ingredientes!$I$132:$I$144) -> 6.7584415 | K27: =IFERROR(J27/D27,0) -> 6.7584415 | L27: =IFERROR(K27/I27,0) -> 0 | M27: =IFERROR(J27/IF(E27>0,E27,SUM(Ingredientes!$E$132:$E$144)),0) -> 11.961843 | N27: =IFERROR(K27/H27,0) -> 0 | O27: 6.7584 | P27: =IFERROR(K27-O27,0) -> 4.1460795e-05
A28: frango-desfiado | B28: Frango Desfiado | C28: Massas e bases | D28: 2 | E28: 2 | F28: MODO DE PREPARO | G28: Não | J28: =SUM(Ingredientes!$I$145:$I$152) -> 45.805887 | K28: =IFERROR(J28/D28,0) -> 22.902943 | L28: =IFERROR(K28/I28,0) -> 0 | M28: =IFERROR(J28/IF(E28>0,E28,SUM(Ingredientes!$E$145:$E$152)),0) -> 22.902943 | N28: =IFERROR(K28/H28,0) -> 0 | O28: 22.2528 | P28: =IFERROR(K28-O28,0) -> 0.65014337
A29: frango-desfiado-com-molho-de-to | B29: Frango Desfiado com Molho de Tomate | C29: Massas e bases | D29: 1 | E29: 1.5692 | F29: MODO DE PREPARO | G29: Não | J29: =SUM(Ingredientes!$I$153:$I$154) -> 54.742973 | K29: =IFERROR(J29/D29,0) -> 54.742973 | L29: =IFERROR(K29/I29,0) -> 0 | M29: =IFERROR(J29/IF(E29>0,E29,SUM(Ingredientes!$E$153:$E$154)),0) -> 34.885912 | N29: =IFERROR(K29/H29,0) -> 0 | O29: 53.353 | P29: =IFERROR(K29-O29,0) -> 1.3899725
A30: frango-com-chuchu-e-molho-branc | B30: Frango com Molho Chuchu e Molho Branco e Arroz com Sementes | C30: Massas e bases | D30: 10 | F30: 10 min | G30: Não | J30: =SUM(Ingredientes!$I$155:$I$160) -> 45.465119 | K30: =IFERROR(J30/D30,0) -> 4.5465119 | L30: =IFERROR(K30/I30,0) -> 0 | M30: =IFERROR(J30/IF(E30>0,E30,SUM(Ingredientes!$E$155:$E$160)),0) -> 16.776797 | N30: =IFERROR(K30/H30,0) -> 0 | O30: 4.5831 | P30: =IFERROR(K30-O30,0) -> -0.03658806
A31: granola-salgada | B31: Granola Salgada | C31: Salgados assados | D31: 4 | F31: MODO DE PREPARO | G31: Não | J31: =SUM(Ingredientes!$I$161:$I$169) -> 39.806375 | K31: =IFERROR(J31/D31,0) -> 9.9515937 | L31: =IFERROR(K31/I31,0) -> 0 | M31: =IFERROR(J31/IF(E31>0,E31,SUM(Ingredientes!$E$161:$E$169)),0) -> 39.806375 | N31: =IFERROR(K31/H31,0) -> 0 | O31: 9.9516 | P31: =IFERROR(K31-O31,0) -> -6.2835661e-06
A32: granola-salgada-30g | B32: Granola Salgada | C32: Salgados assados | D32: 25 | F32: MODO DE PREPARO | G32: Não | J32: =SUM(Ingredientes!$I$170:$I$178) -> 39.806375 | K32: =IFERROR(J32/D32,0) -> 1.592255 | L32: =IFERROR(K32/I32,0) -> 0 | M32: =IFERROR(J32/IF(E32>0,E32,SUM(Ingredientes!$E$170:$E$178)),0) -> 39.806375 | N32: =IFERROR(K32/H32,0) -> 0 | O32: 1.5923 | P32: =IFERROR(K32-O32,0) -> -4.5005371e-05
A33: leite-de-amendoim | B33: Leite de Amendoim | C33: Bebidas | D33: 1 | E33: 1 | F33: MODO DE PREPARO | G33: Não | J33: =SUM(Ingredientes!$I$179:$I$179) -> 3.0612245 | K33: =IFERROR(J33/D33,0) -> 3.0612245 | L33: =IFERROR(K33/I33,0) -> 0 | M33: =IFERROR(J33/IF(E33>0,E33,SUM(Ingredientes!$E$179:$E$179)),0) -> 3.0612245 | N33: =IFERROR(K33/H33,0) -> 0 | O33: 3.0612 | P33: =IFERROR(K33-O33,0) -> 2.4489796e-05
A34: leite-de-arroz | B34: Leite de Arroz Integral | C34: Bebidas | D34: 1 | E34: 1 | F34: MODO DE PREPARO | G34: Não | J34: =SUM(Ingredientes!$I$180:$I$180) -> 1.5306122 | K34: =IFERROR(J34/D34,0) -> 1.5306122 | L34: =IFERROR(K34/I34,0) -> 0 | M34: =IFERROR(J34/IF(E34>0,E34,SUM(Ingredientes!$E$180:$E$180)),0) -> 1.5306122 | N34: =IFERROR(K34/H34,0) -> 0 | O34: 1.5306 | P34: =IFERROR(K34-O34,0) -> 1.2244898e-05
A35: maionese-verde | B35: Maionese Verde | C35: Massas e bases | D35: 1 | E35: 1.8043 | F35: 15 min | G35: Não | J35: =SUM(Ingredientes!$I$181:$I$189) -> 10.933837 | K35: =IFERROR(J35/D35,0) -> 10.933837 | L35: =IFERROR(K35/I35,0) -> 0 | M35: =IFERROR(J35/IF(E35>0,E35,SUM(Ingredientes!$E$181:$E$189)),0) -> 6.0598778 | N35: =IFERROR(K35/H35,0) -> 0 | O35: 10.9338 | P35: =IFERROR(K35-O35,0) -> 3.7493544e-05
A36: porcao-maionese-verde | B36: Maionese Verde | C36: Massas e bases | D36: 2 | F36: MODO DE PREPARO | G36: Não | J36: =SUM(Ingredientes!$I$190:$I$190) -> 0.26719038 | K36: =IFERROR(J36/D36,0) -> 0.13359519 | L36: =IFERROR(K36/I36,0) -> 0 | M36: =IFERROR(J36/IF(E36>0,E36,SUM(Ingredientes!$E$190:$E$190)),0) -> 5.3438076 | N36: =IFERROR(K36/H36,0) -> 0 | O36: 0.1336 | P36: =IFERROR(K36-O36,0) -> -4.8106622e-06
A37: manteiga-vegana | B37: Manteiga Vegana | C37: Massas e bases | D37: 1 | E37: 1 | F37: 10 min | G37: Não | J37: =SUM(Ingredientes!$I$191:$I$193) -> 25.283136 | K37: =IFERROR(J37/D37,0) -> 25.283136 | L37: =IFERROR(K37/I37,0) -> 0 | M37: =IFERROR(J37/IF(E37>0,E37,SUM(Ingredientes!$E$191:$E$193)),0) -> 25.283136 | N37: =IFERROR(K37/H37,0) -> 0 | O37: 25.2831 | P37: =IFERROR(K37-O37,0) -> 3.641246e-05
A38: massa-base-para-pao | B38: Massa Base para Pao | C38: Pães | D38: 1 | F38: 1H | G38: Não | J38: =SUM(Ingredientes!$I$194:$I$204) -> 9.3056069 | K38: =IFERROR(J38/D38,0) -> 9.3056069 | L38: =IFERROR(K38/I38,0) -> 0 | M38: =IFERROR(J38/IF(E38>0,E38,SUM(Ingredientes!$E$194:$E$204)),0) -> 10.845696 | N38: =IFERROR(K38/H38,0) -> 0 | O38: 9.3056 | P38: =IFERROR(K38-O38,0) -> 6.8743287e-06
A39: massa-de-quiche | B39: Massa Low Carb para Quiche | C39: Salgados assados | D39: 20 | F39: 1H | G39: Não | J39: =SUM(Ingredientes!$I$205:$I$210) -> 14.050145 | K39: =IFERROR(J39/D39,0) -> 0.70250723 | L39: =IFERROR(K39/I39,0) -> 0 | M39: =IFERROR(J39/IF(E39>0,E39,SUM(Ingredientes!$E$205:$E$210)),0) -> 14.050145 | N39: =IFERROR(K39/H39,0) -> 0 | O39: 0.7025 | P39: =IFERROR(K39-O39,0) -> 7.2287863e-06
A40: creme-para-quiche | B40: Massa Low Carb para Quiche | C40: Salgados assados | D40: 1 | E40: 1 | F40: 1H | G40: Não | J40: =SUM(Ingredientes!$I$211:$I$215) -> 14.666824 | K40: =IFERROR(J40/D40,0) -> 14.666824 | L40: =IFERROR(K40/I40,0) -> 0 | M40: =IFERROR(J40/IF(E40>0,E40,SUM(Ingredientes!$E$211:$E$215)),0) -> 14.666824 | N40: =IFERROR(K40/H40,0) -> 0 | O40: 14.6668 | P40: =IFERROR(K40-O40,0) -> 2.4489796e-05
A41: creme-para-quiche-vegan | B41: Massa Low Carb para Quiche | C41: Salgados assados | D41: 1 | F41: 1H | G41: Não | J41: =SUM(Ingredientes!$I$216:$I$221) -> 17.261583 | K41: =IFERROR(J41/D41,0) -> 17.261583 | L41: =IFERROR(K41/I41,0) -> 0 | M41: =IFERROR(J41/IF(E41>0,E41,SUM(Ingredientes!$E$216:$E$221)),0) -> 16.132321 | N41: =IFERROR(K41/H41,0) -> 0 | O41: 17.2616 | P41: =IFERROR(K41-O41,0) -> -1.6756176e-05
A42: quiche-de-frango-e-tomate | B42: Massa Low Carb para Quiche | C42: Salgados assados | D42: 1 | F42: 1H | G42: Não | J42: =SUM(Ingredientes!$I$222:$I$225) -> 27.777737 | K42: =IFERROR(J42/D42,0) -> 27.777737 | L42: =IFERROR(K42/I42,0) -> 0 | M42: =IFERROR(J42/IF(E42>0,E42,SUM(Ingredientes!$E$222:$E$225)),0) -> 18.518492 | N42: =IFERROR(K42/H42,0) -> 0 | O42: 20.4426 | P42: =IFERROR(K42-O42,0) -> 7.3351373
A43: massa-esfira | B43: Massa de Esfira | C43: Salgados assados | D43: 1 | E43: 1.3093 | F43: 10 min | G43: Não | J43: =SUM(Ingredientes!$I$226:$I$237) -> 18.314411 | K43: =IFERROR(J43/D43,0) -> 18.314411 | L43: =IFERROR(K43/I43,0) -> 0 | M43: =IFERROR(J43/IF(E43>0,E43,SUM(Ingredientes!$E$226:$E$237)),0) -> 13.987941 | N43: =IFERROR(K43/H43,0) -> 0 | O43: 18.3297 | P43: =IFERROR(K43-O43,0) -> -0.015288614
A44: massa-de-pizza | B44: Massa de Pizza | C44: Massas e bases | D44: 4 | F44: 40 min | G44: Não | J44: =SUM(Ingredientes!$I$238:$I$242) -> 3.8128894 | K44: =IFERROR(J44/D44,0) -> 0.95322234 | L44: =IFERROR(K44/I44,0) -> 0 | M44: =IFERROR(J44/IF(E44>0,E44,SUM(Ingredientes!$E$238:$E$242)),0) -> 7.126896 | N44: =IFERROR(K44/H44,0) -> 0 | O44: 0.9532 | P44: =IFERROR(K44-O44,0) -> 2.2341568e-05
A45: mix-de-sementes-p-pao | B45: Mix de Sementes para Pão | C45: Pães | D45: 1 | E45: 1 | F45: MODO DE PREPARO | G45: Não | J45: =SUM(Ingredientes!$I$243:$I$248) -> 45.921939 | K45: =IFERROR(J45/D45,0) -> 45.921939 | L45: =IFERROR(K45/I45,0) -> 0 | M45: =IFERROR(J45/IF(E45>0,E45,SUM(Ingredientes!$E$243:$E$248)),0) -> 45.921939 | N45: =IFERROR(K45/H45,0) -> 0 | O45: 45.9219 | P45: =IFERROR(K45-O45,0) -> 3.877551e-05
A46: mix-sem-gluten-c-xantana | B46: Mix sem Gluten C/ Xantana | C46: Massas e bases | D46: 1 | F46: MODO DE PREPARO | G46: Não | J46: =SUM(Ingredientes!$I$249:$I$253) -> 16.074551 | K46: =IFERROR(J46/D46,0) -> 16.074551 | L46: =IFERROR(K46/I46,0) -> 0 | M46: =IFERROR(J46/IF(E46>0,E46,SUM(Ingredientes!$E$249:$E$253)),0) -> 10.589296 | N46: =IFERROR(K46/H46,0) -> 0 | O46: 16.0746 | P46: =IFERROR(K46-O46,0) -> -4.8979592e-05
A47: mix-sem-gluten-cris-gutierrez | B47: Mix sem Gluten Cris Gutierrez | C47: Massas e bases | D47: 1 | E47: 0.6129 | F47: 1H | G47: Não | J47: =SUM(Ingredientes!$I$254:$I$257) -> 6.2635918 | K47: =IFERROR(J47/D47,0) -> 6.2635918 | L47: =IFERROR(K47/I47,0) -> 0 | M47: =IFERROR(J47/IF(E47>0,E47,SUM(Ingredientes!$E$254:$E$257)),0) -> 10.219598 | N47: =IFERROR(K47/H47,0) -> 0 | O47: 6.2636 | P47: =IFERROR(K47-O47,0) -> -8.1632653e-06
A48: molho-oriental | B48: Molho Oriental | C48: Massas e bases | D48: 1 | F48: 15 min | G48: Não | J48: =SUM(Ingredientes!$I$258:$I$262) -> 10.052258 | K48: =IFERROR(J48/D48,0) -> 10.052258 | L48: =IFERROR(K48/I48,0) -> 0 | M48: =IFERROR(J48/IF(E48>0,E48,SUM(Ingredientes!$E$258:$E$262)),0) -> 20.942204 | N48: =IFERROR(K48/H48,0) -> 0 | O48: 10.0523 | P48: =IFERROR(K48-O48,0) -> -4.2212675e-05
A49: molho-de-tomate-assado | B49: Molho de Tomate Assado | C49: Massas e bases | D49: 5 | F49: MODO DE PREPARO | G49: Não | J49: =SUM(Ingredientes!$I$263:$I$267) -> 56.609516 | K49: =IFERROR(J49/D49,0) -> 11.321903 | L49: =IFERROR(K49/I49,0) -> 0 | M49: =IFERROR(J49/IF(E49>0,E49,SUM(Ingredientes!$E$263:$E$267)),0) -> 10.610968 | N49: =IFERROR(K49/H49,0) -> 0 | O49: 11.3219 | P49: =IFERROR(K49-O49,0) -> 3.1908609e-06
A50: mussarela-de-caju | B50: Mussarela de Caju | C50: Massas e bases | D50: 1 | F50: 40 min | G50: Não | J50: =SUM(Ingredientes!$I$268:$I$276) -> 11.416299 | K50: =IFERROR(J50/D50,0) -> 11.416299 | L50: =IFERROR(K50/I50,0) -> 0 | M50: =IFERROR(J50/IF(E50>0,E50,SUM(Ingredientes!$E$268:$E$276)),0) -> 12.741405 | N50: =IFERROR(K50/H50,0) -> 0 | O50: 11.4163 | P50: =IFERROR(K50-O50,0) -> -1.0741139e-06
A51: nuggets-de-frango-e-linhaca | B51: Nuggets | C51: Salgados fritos | D51: 9.87 | F51: 1H | G51: Não | J51: =SUM(Ingredientes!$I$277:$I$284) -> 39.912975 | K51: =IFERROR(J51/D51,0) -> 4.0438678 | L51: =IFERROR(K51/I51,0) -> 0 | M51: =IFERROR(J51/IF(E51>0,E51,SUM(Ingredientes!$E$277:$E$284)),0) -> 16.310983 | N51: =IFERROR(K51/H51,0) -> 0 | O51: 4.0439 | P51: =IFERROR(K51-O51,0) -> -3.2232448e-05
A52: pastelzinho-de-festa | B52: Pastelzinho de Festa | C52: Salgados fritos | D52: 25 | F52: 40 min | G52: Não | J52: =SUM(Ingredientes!$I$285:$I$292) -> 22.484505 | K52: =IFERROR(J52/D52,0) -> 0.89938022 | L52: =IFERROR(K52/I52,0) -> 0 | M52: =IFERROR(J52/IF(E52>0,E52,SUM(Ingredientes!$E$285:$E$292)),0) -> 29.584876 | N52: =IFERROR(K52/H52,0) -> 0 | O52: 0.9141 | P52: =IFERROR(K52-O52,0) -> -0.01471978
A53: patinho-acebolado-de-vegetais-a | B53: Patinho Acebolado com Vegetais Assados | C53: Outros | D53: 10 | F53: 10 min | G53: Não | J53: =SUM(Ingredientes!$I$293:$I$299) -> 111.19317 | K53: =IFERROR(J53/D53,0) -> 11.119317 | L53: =IFERROR(K53/I53,0) -> 0 | M53: =IFERROR(J53/IF(E53>0,E53,SUM(Ingredientes!$E$293:$E$299)),0) -> 29.971204 | N53: =IFERROR(K53/H53,0) -> 0 | O53: 11.1193 | P53: =IFERROR(K53-O53,0) -> 1.6726451e-05
A54: pure-de-batatas | B54: Purê de Batatas | C54: Massas e bases | D54: 1 | E54: 1 | F54: 10 min | G54: Não | J54: =SUM(Ingredientes!$I$300:$I$304) -> 12.142728 | K54: =IFERROR(J54/D54,0) -> 12.142728 | L54: =IFERROR(K54/I54,0) -> 0 | M54: =IFERROR(J54/IF(E54>0,E54,SUM(Ingredientes!$E$300:$E$304)),0) -> 12.142728 | N54: =IFERROR(K54/H54,0) -> 0 | O54: 12.199 | P54: =IFERROR(K54-O54,0) -> -0.056272029
A55: pao-lowcarb | B55: Pão Low Carb | C55: Pães | D55: 1 | F55: 20 min | G55: Não | J55: =SUM(Ingredientes!$I$305:$I$315) -> 21.555265 | K55: =IFERROR(J55/D55,0) -> 21.555265 | L55: =IFERROR(K55/I55,0) -> 0 | M55: =IFERROR(J55/IF(E55>0,E55,SUM(Ingredientes!$E$305:$E$315)),0) -> 32.610084 | N55: =IFERROR(K55/H55,0) -> 0 | O55: 21.5553 | P55: =IFERROR(K55-O55,0) -> -3.4693878e-05
A56: pao-roberta | B56: Pão Roberta | C56: Pães | D56: 1 | E56: 0.9885 | F56: 20 min | G56: Não | J56: =SUM(Ingredientes!$I$316:$I$329) -> 9.2327805 | K56: =IFERROR(J56/D56,0) -> 9.2327805 | L56: =IFERROR(K56/I56,0) -> 0 | M56: =IFERROR(J56/IF(E56>0,E56,SUM(Ingredientes!$E$316:$E$329)),0) -> 9.3401927 | N56: =IFERROR(K56/H56,0) -> 0 | O56: 9.2328 | P56: =IFERROR(K56-O56,0) -> -1.9522019e-05
A57: pao-caseiro | B57: Pão Roberta | C57: Pães | D57: 1 | F57: 20 min | G57: Não | J57: =SUM(Ingredientes!$I$330:$I$342) -> 8.2596665 | K57: =IFERROR(J57/D57,0) -> 8.2596665 | L57: =IFERROR(K57/I57,0) -> 0 | M57: =IFERROR(J57/IF(E57>0,E57,SUM(Ingredientes!$E$330:$E$342)),0) -> 11.535847 | N57: =IFERROR(K57/H57,0) -> 0 | O57: 8.2597 | P57: =IFERROR(K57-O57,0) -> -3.3512352e-05
A58: pao-func-sanduiche | B58: Pão Sanduiche | C58: Pães | D58: 12 | F58: 20 min | G58: Não | J58: =SUM(Ingredientes!$I$343:$I$356) -> 13.350435 | K58: =IFERROR(J58/D58,0) -> 1.1125362 | L58: =IFERROR(K58/I58,0) -> 0 | M58: =IFERROR(J58/IF(E58>0,E58,SUM(Ingredientes!$E$343:$E$356)),0) -> 9.8892108 | N58: =IFERROR(K58/H58,0) -> 0 | O58: 1.1125 | P58: =IFERROR(K58-O58,0) -> 3.6217777e-05
A59: pao-de-forma-low-carb | B59: Pão de Forma Low Carb | C59: Pães | D59: 1 | F59: 40 min | G59: Não | J59: =SUM(Ingredientes!$I$357:$I$363) -> 22.482245 | K59: =IFERROR(J59/D59,0) -> 22.482245 | L59: =IFERROR(K59/I59,0) -> 0 | M59: =IFERROR(J59/IF(E59>0,E59,SUM(Ingredientes!$E$357:$E$363)),0) -> 28.279553 | N59: =IFERROR(K59/H59,0) -> 0 | O59: 22.4822 | P59: =IFERROR(K59-O59,0) -> 4.4897959e-05
A60: pao-de-milho | B60: Pão de Milho | C60: Pães | D60: 1 | F60: 30 min | G60: Não | J60: =SUM(Ingredientes!$I$364:$I$373) -> 10.138612 | K60: =IFERROR(J60/D60,0) -> 10.138612 | L60: =IFERROR(K60/I60,0) -> 0 | M60: =IFERROR(J60/IF(E60>0,E60,SUM(Ingredientes!$E$364:$E$373)),0) -> 12.817462 | N60: =IFERROR(K60/H60,0) -> 0 | O60: 10.1386 | P60: =IFERROR(K60-O60,0) -> 1.2244898e-05
A61: pao-de-q | B61: Pão de Q? | C61: Pães | D61: 10 | F61: 2HR | G61: Não | J61: =SUM(Ingredientes!$I$374:$I$382) -> 15.581358 | K61: =IFERROR(J61/D61,0) -> 1.5581358 | L61: =IFERROR(K61/I61,0) -> 0 | M61: =IFERROR(J61/IF(E61>0,E61,SUM(Ingredientes!$E$374:$E$382)),0) -> 9.1332698 | N61: =IFERROR(K61/H61,0) -> 0 | O61: 1.5581 | P61: =IFERROR(K61-O61,0) -> 3.5823638e-05
A62: burger-de-grao-de-bico-e-bete | B62: Pão de Q? | C62: Pães | D62: 12 | F62: 2HR | G62: Não | J62: =SUM(Ingredientes!$I$383:$I$393) -> 23.555461 | K62: =IFERROR(J62/D62,0) -> 1.9629551 | L62: =IFERROR(K62/I62,0) -> 0 | M62: =IFERROR(J62/IF(E62>0,E62,SUM(Ingredientes!$E$383:$E$393)),0) -> 13.233405 | N62: =IFERROR(K62/H62,0) -> 0 | O62: 1.963 | P62: =IFERROR(K62-O62,0) -> -4.488174e-05
A63: pao-de-sementes | B63: Pão de Sementes | C63: Pães | D63: 8 | F63: 30 min | G63: Não | J63: =SUM(Ingredientes!$I$394:$I$402) -> 21.704565 | K63: =IFERROR(J63/D63,0) -> 2.7130706 | L63: =IFERROR(K63/I63,0) -> 0 | M63: =IFERROR(J63/IF(E63>0,E63,SUM(Ingredientes!$E$394:$E$402)),0) -> 29.937331 | N63: =IFERROR(K63/H63,0) -> 0 | O63: 2.6939 | P63: =IFERROR(K63-O63,0) -> 0.019170623
A64: pao-nobis | B64: Pão-nóbis | C64: Pães | D64: 1 | F64: 1HR | G64: Não | J64: =SUM(Ingredientes!$I$403:$I$413) -> 9.9679694 | K64: =IFERROR(J64/D64,0) -> 9.9679694 | L64: =IFERROR(K64/I64,0) -> 0 | M64: =IFERROR(J64/IF(E64>0,E64,SUM(Ingredientes!$E$403:$E$413)),0) -> 11.85252 | N64: =IFERROR(K64/H64,0) -> 0 | O64: 9.968 | P64: =IFERROR(K64-O64,0) -> -3.0612245e-05
A65: quiche-de-ricota-e-alho-poro | B65: Quiche Ricota, Ora-pro-nóbis e Alho-poró | C65: Salgados assados | D65: 8 | F65: 1H | G65: Não | J65: =SUM(Ingredientes!$I$414:$I$417) -> 37.911116 | K65: =IFERROR(J65/D65,0) -> 4.7388895 | L65: =IFERROR(K65/I65,0) -> 0 | M65: =IFERROR(J65/IF(E65>0,E65,SUM(Ingredientes!$E$414:$E$417)),0) -> 22.300657 | N65: =IFERROR(K65/H65,0) -> 0 | O65: 3.8608 | P65: =IFERROR(K65-O65,0) -> 0.87808951
A66: quiche-vegan-broc-e-cebola-roxa | B66: Quiche Ricota, Ora-pro-nóbis e Alho-poró | C66: Salgados assados | D66: 8 | F66: 1H | G66: Não | J66: =SUM(Ingredientes!$I$418:$I$421) -> 30.513138 | K66: =IFERROR(J66/D66,0) -> 3.8141423 | L66: =IFERROR(K66/I66,0) -> 0 | M66: =IFERROR(J66/IF(E66>0,E66,SUM(Ingredientes!$E$418:$E$421)),0) -> 17.948905 | N66: =IFERROR(K66/H66,0) -> 0 | O66: 2.4091 | P66: =IFERROR(K66-O66,0) -> 1.4050423
A67: quiche-tomate-e-manj-vegan | B67: Quiche Ricota, Ora-pro-nóbis e Alho-poró | C67: Salgados assados | D67: 10 | F67: 1H | G67: Não | J67: =SUM(Ingredientes!$I$422:$I$425) -> 33.383725 | K67: =IFERROR(J67/D67,0) -> 3.3383725 | L67: =IFERROR(K67/I67,0) -> 0 | M67: =IFERROR(J67/IF(E67>0,E67,SUM(Ingredientes!$E$422:$E$425)),0) -> 16.860467 | N67: =IFERROR(K67/H67,0) -> 0 | O67: 2.2846 | P67: =IFERROR(K67-O67,0) -> 1.0537725
A68: copy-of-quiche-de-ricota-e-alho | B68: Quiche Ricota, Ora-pro-nóbis e Espinafre | C68: Salgados assados | D68: 8 | F68: 1H | G68: Não | J68: =SUM(Ingredientes!$I$426:$I$428) -> 14.484082 | K68: =IFERROR(J68/D68,0) -> 1.8105103 | L68: =IFERROR(K68/I68,0) -> 0 | M68: =IFERROR(J68/IF(E68>0,E68,SUM(Ingredientes!$E$426:$E$428)),0) -> 13.794364 | N68: =IFERROR(K68/H68,0) -> 0 | O68: 1.108 | P68: =IFERROR(K68-O68,0) -> 0.70251029
A69: recheio-de-carne | B69: Recheio de Carne | C69: Massas e bases | D69: 1 | F69: 10 min | G69: Não | J69: =SUM(Ingredientes!$I$429:$I$430) -> 63.42437 | K69: =IFERROR(J69/D69,0) -> 63.42437 | L69: =IFERROR(K69/I69,0) -> 0 | M69: =IFERROR(J69/IF(E69>0,E69,SUM(Ingredientes!$E$429:$E$430)),0) -> 55.151626 | N69: =IFERROR(K69/H69,0) -> 0 | O69: 63.4244 | P69: =IFERROR(K69-O69,0) -> -3.0252101e-05
A70: requeiju | B70: Requeiju | C70: Massas e bases | D70: 1 | E70: 1.0632 | F70: 10 min | G70: Não | J70: =SUM(Ingredientes!$I$431:$I$437) -> 17.82931 | K70: =IFERROR(J70/D70,0) -> 17.82931 | L70: =IFERROR(K70/I70,0) -> 0 | M70: =IFERROR(J70/IF(E70>0,E70,SUM(Ingredientes!$E$431:$E$437)),0) -> 16.769479 | N70: =IFERROR(K70/H70,0) -> 0 | O70: 17.8293 | P70: =IFERROR(K70-O70,0) -> 9.6670247e-06
A71: porcao-requeiju | B71: Requeiju | C71: Massas e bases | D71: 1 | F71: MODO DE PREPARO | G71: Não | J71: =SUM(Ingredientes!$I$438:$I$438) -> 0.5684569 | K71: =IFERROR(J71/D71,0) -> 0.5684569 | L71: =IFERROR(K71/I71,0) -> 0 | M71: =IFERROR(J71/IF(E71>0,E71,SUM(Ingredientes!$E$438:$E$438)),0) -> 14.211423 | N71: =IFERROR(K71/H71,0) -> 0 | O71: 0.5685 | P71: =IFERROR(K71-O71,0) -> -4.3097683e-05
A72: sanduba-veg | B72: Sanduba Veg | C72: Sanduíches | D72: 1 | F72: MODO DE PREPARO | G72: Não | J72: =SUM(Ingredientes!$I$439:$I$443) -> 1.7344443 | K72: =IFERROR(J72/D72,0) -> 1.7344443 | L72: =IFERROR(K72/I72,0) -> 0 | M72: =IFERROR(J72/IF(E72>0,E72,SUM(Ingredientes!$E$439:$E$443)),0) -> 9.9111101 | N72: =IFERROR(K72/H72,0) -> 0 | O72: 0.7863 | P72: =IFERROR(K72-O72,0) -> 0.94814426
A73: sanduba-violeta | B73: Sanduba Violeta | C73: Sanduíches | D73: 1 | F73: MODO DE PREPARO | G73: Não | J73: =SUM(Ingredientes!$I$444:$I$446) -> 0.44017747 | K73: =IFERROR(J73/D73,0) -> 0.44017747 | L73: =IFERROR(K73/I73,0) -> 0 | M73: =IFERROR(J73/IF(E73>0,E73,SUM(Ingredientes!$E$444:$E$446)),0) -> 5.8690329 | N73: =IFERROR(K73/H73,0) -> 0 | O73: 0.4402 | P73: =IFERROR(K73-O73,0) -> -2.2532181e-05
A74: suco-nobis | B74: Suco-nóbis | C74: Bebidas | D74: 1 | F74: 5 min | G74: Não | J74: =SUM(Ingredientes!$I$447:$I$451) -> 0.88685452 | K74: =IFERROR(J74/D74,0) -> 0.88685452 | L74: =IFERROR(K74/I74,0) -> 0 | M74: =IFERROR(J74/IF(E74>0,E74,SUM(Ingredientes!$E$447:$E$451)),0) -> 2.5557767 | N74: =IFERROR(K74/H74,0) -> 0 | O74: 0.8869 | P74: =IFERROR(K74-O74,0) -> -4.5482755e-05
A75: torta-low-carb-de-brocolis-e-ri | B75: Torta Low Carb de Brocolis e Ricota | C75: Salgados assados | D75: 1 | F75: 40 min | G75: Não | J75: =SUM(Ingredientes!$I$452:$I$460) -> 41.531354 | K75: =IFERROR(J75/D75,0) -> 41.531354 | L75: =IFERROR(K75/I75,0) -> 0 | M75: =IFERROR(J75/IF(E75>0,E75,SUM(Ingredientes!$E$452:$E$460)),0) -> 24.973755 | N75: =IFERROR(K75/H75,0) -> 0 | O75: 41.5314 | P75: =IFERROR(K75-O75,0) -> -4.5594192e-05
A76: torta-de-frango-sem-ovos | B76: Torta de Frango sem Ovos | C76: Salgados assados | D76: 20 | F76: 10 min | G76: Não | J76: =SUM(Ingredientes!$I$461:$I$466) -> 24.142515 | K76: =IFERROR(J76/D76,0) -> 1.2071257 | L76: =IFERROR(K76/I76,0) -> 0 | M76: =IFERROR(J76/IF(E76>0,E76,SUM(Ingredientes!$E$461:$E$466)),0) -> 17.883344 | N76: =IFERROR(K76/H76,0) -> 0 | O76: 1.1916 | P76: =IFERROR(K76-O76,0) -> 0.015525747

Sheet Ingredientes
A1: Ingredientes das receitas
A2: Uma linha por ingrediente de cada receita. É daqui que sai o custo de cada produto.
A3: Código do produto | B3: Produto | C3: Código do insumo | D3: Insumo | E3: Quantidade (kg) | F3: Fator de correção | G3: Peso bruto | H3: Preço por quilo | I3: Custo
A4: caldo-de-batata-doce | B4: Caldo de Batata Doce | C4: caldo-de-frango | D4: Caldo de Frango | E4: 2 | F4: =IFERROR(INDEX(Insumos!$F$4:$F$168,MATCH($C4,Insumos!$A$4:$A$168,0)),1) -> 0.98 | G4: =IFERROR(E4/F4,0) -> 2.0408163 | H4: =IFERROR(INDEX(Insumos!$G$20:$G$168,MATCH($C4,Insumos!$A$20:$A$168,0)),0) -> 10 | I4: =G4*H4 -> 20.408163
A5: caldo-de-batata-doce | B5: Caldo de Batata Doce | C5: batata-doce-crua-sem-casca | D5: Batata Doce Crua sem Casca | E5: 1 | F5: =IFERROR(INDEX(Insumos!$F$4:$F$168,MATCH($C5,Insumos!$A$4:$A$168,0)),1) -> 0.86142797 | G5: =IFERROR(E5/F5,0) -> 1.1608632 | H5: =IFERROR(INDEX(Insumos!$G$20:$G$168,MATCH($C5,Insumos!$A$20:$A$168,0)),0) -> 5.69 | I5: =G5*H5 -> 6.6053114
A6: caldo-de-batata-doce | B6: Caldo de Batata Doce | C6: sal-integral | D6: Sal Integral | E6: 0.02 | F6: =IFERROR(INDEX(Insumos!$F$4:$F$168,MATCH($C6,Insumos!$A$4:$A$168,0)),1) -> 0.98 | G6: =IFERROR(E6/F6,0) -> 0.020408163 | H6: =IFERROR(INDEX(Insumos!$G$20:$G$168,MATCH($C6,Insumos!$A$20:$A$168,0)),0) -> 5 | I6: =G6*H6 -> 0.10204082
A7: caldo-de-batata-doce | B7: Caldo de Batata Doce | C7: pimenta-do-reino | D7: Pimenta-do-reino | E7: 0.005 | F7: =IFERROR(INDEX(Insumos!$F$4:$F$168,MATCH($C7,Insumos!$A$4:$A$168,0)),1) -> 0.95 | G7: =IFERROR(E7/F7,0) -> 0.0052631579 | H7: =IFERROR(INDEX(Insumos!$G$20:$G$168,MATCH($C7,Insumos!$A$20:$A$168,0)),0) -> 25.16 | I7: =G7*H7 -> 0.13242105
A8: caldo-de-batata-doce | B8: Caldo de Batata Doce | C8: curry | D8: Curry | E8: 0.01 | F8: =IFERROR(INDEX(Insumos!$F$4:$F$168,MATCH($C8,Insumos!$A$4:$A$168,0)),1) -> 0.98 | G8: =IFERROR(E8/F8,0) -> 0.010204082 | H8: =IFERROR(INDEX(Insumos!$G$20:$G$168,MATCH($C8,Insumos!$A$20:$A$168,0)),0) -> 9.54 | I8: =G8*H8 -> 0.097346939
A9: caldo-de-batata-doce | B9: Caldo de Batata Doce | C9: noz-moscada | D9: Noz-moscada | E9: 0.005 | F9: =IFERROR(INDEX(Insumos!$F$4:$F$168,MATCH($C9,Insumos!$A$4:$A$168,0)),1) -> 0.98 | G9: =IFERROR(E9/F9,0) -> 0.0051020408 | H9: =IFERROR(INDEX(Insumos!$G$20:$G$168,MATCH($C9,Insumos!$A$20:$A$168,0)),0) -> 105 | I9: =G9*H9 -> 0.53571429
A10: caldo-de-batata-doce | B10: Caldo de Batata Doce | C10: frango-desfiado | D10: Frango Desfiado | E10: 0.45 | F10: =IFERROR(INDEX(Insumos!$F$4:$F$168,MATCH($C10,Insumos!$A$4:$A$168,0)),1) -> 0.5 | G10: =IFERROR(E10/F10,0) -> 0.9 | H10: =Insumos!$G$6 -> 22.902943 | I10: =G10*H10 -> 20.612649
A11: caldo-de-cabotia | B11: Caldo de Cabotia | C11: caldo-de-frango | D11: Caldo de Frango | E11: 2 | F11: =IFERROR(INDEX(Insumos!$F$4:$F$168,MATCH($C11,Insumos!$A$4:$A$168,0)),1) -> 0.98 | G11: =IFERROR(E11/F11,0) -> 2.0408163 | H11: =IFERROR(INDEX(Insumos!$G$20:$G$168,MATCH($C11,Insumos!$A$20:$A$168,0)),0) -> 10 | I11: =G11*H11 -> 20.408163
A12: caldo-de-cabotia | B12: Caldo de Cabotia | C12: abobora-cabotia | D12: Abobora Cabotia | E12: 1 | F12: =IFERROR(INDEX(Insumos!$F$4:$F$168,MATCH($C12,Insumos!$A$4:$A$168,0)),1) -> 0.97 | G12: =IFERROR(E12/F12,0) -> 1.0309278 | H12: =IFERROR(INDEX(Insumos!$G$20:$G$168,MATCH($C12,Insumos!$A$20:$A$168,0)),0) -> 6 | I12: =G12*H12 -> 6.185567
A13: caldo-de-cabotia | B13: Caldo de Cabotia | C13: sal-integral | D13: Sal Integral | E13: 0.02 | F13: =IFERROR(INDEX(Insumos!$F$4:$F$168,MATCH($C13,Insumos!$A$4:$A$168,0)),1) -> 0.98 | G13: =IFERROR(E13/F13,0) -> 0.020408163 | H13: =IFERROR(INDEX(Insumos!$G$20:$G$168,MATCH($C13,Insumos!$A$20:$A$168,0)),0) -> 5 | I13: =G13*H13 -> 0.10204082
A14: caldo-de-cabotia | B14: Caldo de Cabotia | C14: pimenta-do-reino | D14: Pimenta-do-reino | E14: 0.005 | F14: =IFERROR(INDEX(Insumos!$F$4:$F$168,MATCH($C14,Insumos!$A$4:$A$168,0)),1) -> 0.95 | G14: =IFERROR(E14/F14,0) -> 0.0052631579 | H14: =IFERROR(INDEX(Insumos!$G$20:$G$168,MATCH($C14,Insumos!$A$20:$A$168,0)),0) -> 25.16 | I14: =G14*H14 -> 0.13242105
A15: caldo-de-cabotia | B15: Caldo de Cabotia | C15: curry | D15: Curry | E15: 0.01 | F15: =IFERROR(INDEX(Insumos!$F$4:$F$168,MATCH($C15,Insumos!$A$4:$A$168,0)),1) -> 0.98 | G15: =IFERROR(E15/F15,0) -> 0.010204082 | H15: =IFERROR(INDEX(Insumos!$G$20:$G$168,MATCH($C15,Insumos!$A$20:$A$168,0)),0) -> 9.54 | I15: =G15*H15 -> 0.097346939
A16: caldo-de-cabotia | B16: Caldo de Cabotia | C16: noz-moscada | D16: Noz-moscada | E16: 0.005 | F16: =IFERROR(INDEX(Insumos!$F$4:$F$168,MATCH($C16,Insumos!$A$4:$A$168,0)),1) -> 0.98 | G16: =IFERROR(E16/F16,0) -> 0.0051020408 | H16: =IFERROR(INDEX(Insumos!$G$20:$G$168,MATCH($C16,Insumos!$A$20:$A$168,0)),0) -> 105 | I16: =G16*H16 -> 0.53571429
A17: caldo-de-cabotia | B17: Caldo de Cabotia | C17: frango-desfiado | D17: Frango Desfiado | E17: 0.45 | F17: =IFERROR(INDEX(Insumos!$F$4:$F$168,MATCH($C17,Insumos!$A$4:$A$168,0)),1) -> 0.5 | G17: =IFERROR(E17/F17,0) -> 0.9 | H17: =Insumos!$G$6 -> 22.902943 | I17: =G17*H17 -> 20.612649
A18: caldo-de-legumes-e-frango | B18: Caldo de Legumes e Frango | C18: caldo-de-frango | D18: Caldo de Frango | E18: 2 | F18: =IFERROR(INDEX(Insumos!$F$4:$F$168,MATCH($C18,Insumos!$A$4:$A$168,0)),1) -> 0.98 | G18: =IFERROR(E18/F18,0) -> 2.0408163 | H18: =IFERROR(INDEX(Insumos!$G$20:$G$168,MATCH($C18,Insumos!$A$20:$A$168,0)),0) -> 10 | I18: =G18*H18 -> 20.408163
A19: caldo-de-legumes-e-frango | B19: Caldo de Legumes e Frango | C19: batata-monalisa-in-natura | D19: Batata Monalisa In Natura | E19: 0.25 | F19: =IFERROR(INDEX(Insumos!$F$4:$F$168,MATCH($C19,Insumos!$A$4:$A$168,0)),1) -> 0.8 | G19: =IFERROR(E19/F19,0) -> 0.3125 | H19: =IFERROR(INDEX(Insumos!$G$20:$G$168,MATCH($C19,Insumos!$A$20:$A$168,0)),0) -> 6 | I19: =G19*H19 -> 1.875
A20: caldo-de-legumes-e-frango | B20: Caldo de Legumes e Frango | C20: sal-integral | D20: Sal Integral | E20: 0.02 | F20: =IFERROR(INDEX(Insumos!$F$4:$F$168,MATCH($C20,Insumos!$A$4:$A$168,0)),1) -> 0.98 | G20: =IFERROR(E20/F20,0) -> 0.020408163 | H20: =IFERROR(INDEX(Insumos!$G$20:$G$168,MATCH($C20,Insumos!$A$20:$A$168,0)),0) -> 5 | I20: =G20*H20 -> 0.10204082
A21: caldo-de-legumes-e-frango | B21: Caldo de Legumes e Frango | C21: pimenta-do-reino | D21: Pimenta-do-reino | E21: 0.005 | F21: =IFERROR(INDEX(Insumos!$F$4:$F$168,MATCH($C21,Insumos!$A$4:$A$168,0)),1) -> 0.95 | G21: =IFERROR(E21/F21,0) -> 0.0052631579 | H21: =IFERROR(INDEX(Insumos!$G$20:$G$168,MATCH($C21,Insumos!$A$20:$A$168,0)),0) -> 25.16 | I21: =G21*H21 -> 0.13242105
A22: caldo-de-legumes-e-frango | B22: Caldo de Legumes e Frango | C22: curry | D22: Curry | E22: 0.01 | F22: =IFERROR(INDEX(Insumos!$F$4:$F$168,MATCH($C22,Insumos!$A$4:$A$168,0)),1) -> 0.98 | G22: =IFERROR(E22/F22,0) -> 0.010204082 | H22: =IFERROR(INDEX(Insumos!$G$20:$G$168,MATCH($C22,Insumos!$A$20:$A$168,0)),0) -> 9.54 | I22: =G22*H22 -> 0.097346939
A23: caldo-de-legumes-e-frango | B23: Caldo de Legumes e Frango | C23: noz-moscada | D23: Noz-moscada | E23: 0.005 | F23: =IFERROR(INDEX(Insumos!$F$4:$F$168,MATCH($C23,Insumos!$A$4:$A$168,0)),1) -> 0.98 | G23: =IFERROR(E23/F23,0) -> 0.0051020408 | H23: =IFERROR(INDEX(Insumos!$G$20:$G$168,MATCH($C23,Insumos!$A$20:$A$168,0)),0) -> 105 | I23: =G23*H23 -> 0.53571429
A24: caldo-de-legumes-e-frango | B24: Caldo de Legumes e Frango | C24: frango-desfiado | D24: Frango Desfiado | E24: 0.45 | F24: =IFERROR(INDEX(Insumos!$F$4:$F$168,MATCH($C24,Insumos!$A$4:$A$168,0)),1) -> 0.5 | G24: =IFERROR(E24/F24,0) -> 0.9 | H24: =Insumos!$G$6 -> 22.902943 | I24: =G24*H24 -> 20.612649
A25: caldo-de-legumes-e-frango | B25: Caldo de Legumes e Frango | C25: brocolis | D25: Brócolis | E25: 0.25 | F25: =IFERROR(INDEX(Insumos!$F$4:$F$168,MATCH($C25,Insumos!$A$4:$A$168,0)),1) -> 0.95 | G25: =IFERROR(E25/F25,0) -> 0.26315789 | H25: =IFERROR(INDEX(Insumos!$G$20:$G$168,MATCH($C25,Insumos!$A$20:$A$168,0)),0) -> 30 | I25: =G25*H25 -> 7.8947368
A26: caldo-de-legumes-e-frango | B26: Caldo de Legumes e Frango | C26: cenoura-com-casca | D26: Cenoura com Casca | E26: 0.25 | F26: =IFERROR(INDEX(Insumos!$F$4:$F$168,MATCH($C26,Insumos!$A$4:$A$168,0)),1) -> 0.98 | G26: =IFERROR(E26/F26,0) -> 0.25510204 | H26: =IFERROR(INDEX(Insumos!$G$20:$G$168,MATCH($C26,Insumos!$A$20:$A$168,0)),0) -> 7.9 | I26: =G26*H26 -> 2.0153061
A27: caldo-de-legumes-e-frango | B27: Caldo de Legumes e Frango | C27: chuchu | D27: Chuchu | E27: 0.25 | F27: =IFERROR(INDEX(Insumos!$F$4:$F$168,MATCH($C27,Insumos!$A$4:$A$168,0)),1) -> 0.95 | G27: =IFERROR(E27/F27,0) -> 0.26315789 | H27: =IFERROR(INDEX(Insumos!$G$20:$G$168,MATCH($C27,Insumos!$A$20:$A$168,0)),0) -> 7 | I27: =G27*H27 -> 1.8421053
A28: coxinha-de-batata-doce | B28: Coxinha Massa Trad | C28: frango-desfiado-com-molho-de-tomate | D28: Frango Desfiado com Molho de Tomate | E28: 0.75 | F28: =IFERROR(INDEX(Insumos!$F$4:$F$168,MATCH($C28,Insumos!$A$4:$A$168,0)),1) -> 1 | G28: =IFERROR(E28/F28,0) -> 0.75 | H28: =Insumos!$G$7 -> 34.885912 | I28: =G28*H28 -> 26.164434
A29: coxinha-de-batata-doce | B29: Coxinha Massa Trad | C29: linhaca-dourada | D29: Linhaça Dourada | E29: 0.5 | F29: =IFERROR(INDEX(Insumos!$F$4:$F$168,MATCH($C29,Insumos!$A$4:$A$168,0)),1) -> 0.98 | G29: =IFERROR(E29/F29,0) -> 0.51020408 | H29: =IFERROR(INDEX(Insumos!$G$20:$G$168,MATCH($C29,Insumos!$A$20:$A$168,0)),0) -> 28.75 | I29: =G29*H29 -> 14.668367
A30: coxinha-de-batata-doce | B30: Coxinha Massa Trad | C30: batata-doce-cozida-no-vapor | D30: Batata Doce Cozida No Vapor | E30: 2.039 | F30: =IFERROR(INDEX(Insumos!$F$4:$F$168,MATCH($C30,Insumos!$A$4:$A$168,0)),1) -> 0.94016675 | G30: =IFERROR(E30/F30,0) -> 2.1687642 | H30: =IFERROR(INDEX(Insumos!$G$20:$G$168,MATCH($C30,Insumos!$A$20:$A$168,0)),0) -> 12 | I30: =G30*H30 -> 26.025171
A31: coxinha-de-batata-doce | B31: Coxinha Massa Trad | C31: ovos | D31: Ovos | E31: 0.1 | F31: =IFERROR(INDEX(Insumos!$F$4:$F$168,MATCH($C31,Insumos!$A$4:$A$168,0)),1) -> 1 | G31: =IFERROR(E31/F31,0) -> 0.1 | H31: =IFERROR(INDEX(Insumos!$G$20:$G$168,MATCH($C31,Insumos!$A$20:$A$168,0)),0) -> 15 | I31: =G31*H31 -> 1.5
A32: coxinha-de-batata-doce | B32: Coxinha Massa Trad | C32: agua | D32: Água | E32: 0.15 | F32: =IFERROR(INDEX(Insumos!$F$4:$F$168,MATCH($C32,Insumos!$A$4:$A$168,0)),1) -> 0.98 | G32: =IFERROR(E32/F32,0) -> 0.15306122 | H32: =IFERROR(INDEX(Insumos!$G$20:$G$168,MATCH($C32,Insumos!$A$20:$A$168,0)),0) -> 1.5 | I32: =G32*H32 -> 0.22959184
A33: cracker-sem-gluten | B33: Cracker sem Glúten | C33: farinha-de-arroz-integral | D33: Farinha de Arroz Integral | E33: 0.15 | F33: =IFERROR(INDEX(Insumos!$F$4:$F$168,MATCH($C33,Insumos!$A$4:$A$168,0)),1) -> 0.98 | G33: =IFERROR(E33/F33,0) -> 0.15306122 | H33: =IFERROR(INDEX(Insumos!$G$20:$G$168,MATCH($C33,Insumos!$A$20:$A$168,0)),0) -> 9.5 | I33: =G33*H33 -> 1.4540816
A34: cracker-sem-gluten | B34: Cracker sem Glúten | C34: polvilho-doce | D34: Polvilho Doce | E34: 0.065 | F34: =IFERROR(INDEX(Insumos!$F$4:$F$168,MATCH($C34,Insumos!$A$4:$A$168,0)),1) -> 0.98 | G34: =IFERROR(E34/F34,0) -> 0.066326531 | H34: =IFERROR(INDEX(Insumos!$G$20:$G$168,MATCH($C34,Insumos!$A$20:$A$168,0)),0) -> 12 | I34: =G34*H34 -> 0.79591837
A35: cracker-sem-gluten | B35: Cracker sem Glúten | C35: psyllium | D35: Psyllium | E35: 0.015 | F35: =IFERROR(INDEX(Insumos!$F$4:$F$168,MATCH($C35,Insumos!$A$4:$A$168,0)),1) -> 0.98 | G35: =IFERROR(E35/F35,0) -> 0.015306122 | H35: =IFERROR(INDEX(Insumos!$G$20:$G$168,MATCH($C35,Insumos!$A$20:$A$168,0)),0) -> 54.4 | I35: =G35*H35 -> 0.83265306
A36: cracker-sem-gluten | B36: Cracker sem Glúten | C36: acucar-demerara | D36: Açucar Demerara | E36: 0.01 | F36: =IFERROR(INDEX(Insumos!$F$4:$F$168,MATCH($C36,Insumos!$A$4:$A$168,0)),1) -> 0.98 | G36: =IFERROR(E36/F36,0) -> 0.010204082 | H36: =IFERROR(INDEX(Insumos!$G$20:$G$168,MATCH($C36,Insumos!$A$20:$A$168,0)),0) -> 6 | I36: =G36*H36 -> 0.06122449
A37: cracker-sem-gluten | B37: Cracker sem Glúten | C37: sal-integral | D37: Sal Integral | E37: 0.005 | F37: =IFERROR(INDEX(Insumos!$F$4:$F$168,MATCH($C37,Insumos!$A$4:$A$168,0)),1) -> 0.98 | G37: =IFERROR(E37/F37,0) -> 0.0051020408 | H37: =IFERROR(INDEX(Insumos!$G$20:$G$168,MATCH($C37,Insumos!$A$20:$A$168,0)),0) -> 5 | I37: =G37*H37 -> 0.025510204
A38: cracker-sem-gluten | B38: Cracker sem Glúten | C38: goma-xantana | D38: Goma Xantana | E38: 0.0005 | F38: =IFERROR(INDEX(Insumos!$F$4:$F$168,MATCH($C38,Insumos!$A$4:$A$168,0)),1) -> 0.98 | G38: =IFERROR(E38/F38,0) -> 0.00051020408 | H38: =IFERROR(INDEX(Insumos!$G$20:$G$168,MATCH($C38,Insumos!$A$20:$A$168,0)),0) -> 36.86 | I38: =G38*H38 -> 0.018806122
A39: cracker-sem-gluten | B39: Cracker sem Glúten | C39: fermento-biologico-seco | D39: Fermento Biologico Seco | E39: 0.01 | F39: =IFERROR(INDEX(Insumos!$F$4:$F$168,MATCH($C39,Insumos!$A$4:$A$168,0)),1) -> 0.98 | G39: =IFERROR(E39/F39,0) -> 0.010204082 | H39: =IFERROR(INDEX(Insumos!$G$20:$G$168,MATCH($C39,Insumos!$A$20:$A$168,0)),0) -> 14.9 | I39: =G39*H39 -> 0.15204082
A40: cracker-sem-gluten | B40: Cracker sem Glúten | C40: azeite-de-oliva | D40: Azeite de Oliva | E40: 0.03 | F40: =IFERROR(INDEX(Insumos!$F$4:$F$168,MATCH($C40,Insumos!$A$4:$A$168,0)),1) -> 0.95 | G40: =IFERROR(E40/F40,0) -> 0.031578947 | H40: =IFERROR(INDEX(Insumos!$G$20:$G$168,MATCH($C40,Insumos!$A$20:$A$168,0)),0) -> 20 | I40: =G40*H40 -> 0.63157895
... A46: esfira-de-carne | B46: Esfira de Carne | C46: recheio-de-carne-para-esfira | D46: Recheio de Carne para Esfira | E46: 1.2 | F46: =IFERROR(INDEX(Insumos!$F$4:$F$168,MATCH($C46,Insumos!$A$4:$A$168,0)),1) -> 1 | G46: =IFERROR(E46/F46,0) -> 1.2 | H46: =IFERROR(INDEX(Insumos!$G$20:$G$168,MATCH($C46,Insumos!$A$20:$A$168,0)),0) -> 60 | I46: =G46*H46 -> 72
A47: esfira-de-carne | B47: Esfira de Carne | C47: massa-de-esfira | D47: Massa de Esfira | E47: 1.36 | F47: =IFERROR(INDEX(Insumos!$F$4:$F$168,MATCH($C47,Insumos!$A$4:$A$168,0)),1) -> 1 | G47: =IFERROR(E47/F47,0) -> 1.36 | H47: =Insumos!$G$13 -> 13.987941 | I47: =G47*H47 -> 19.0236
A48: massa-mini-pizza | B48: Massa Mini Pizza | C48: mix-sem-gluten-c-goma-xantana | D48: Mix sem Glúten C/ Goma Xantana | E48: 0.18 | F48: =IFERROR(INDEX(Insumos!$F$4:$F$168,MATCH($C48,Insumos!$A$4:$A$168,0)),1) -> 0.98 | G48: =IFERROR(E48/F48,0) -> 0.18367347 | H48: =IFERROR(INDEX(Insumos!$G$20:$G$168,MATCH($C48,Insumos!$A$20:$A$168,0)),0) -> 16.0746 | I48: =G48*H48 -> 2.9524776
A49: massa-mini-pizza | B49: Massa Mini Pizza | C49: fermento-biologico-seco | D49: Fermento Biologico Seco | E49: 0.005 | F49: =IFERROR(INDEX(Insumos!$F$4:$F$168,MATCH($C49,Insumos!$A$4:$A$168,0)),1) -> 0.98 | G49: =IFERROR(E49/F49,0) -> 0.0051020408 | H49: =IFERROR(INDEX(Insumos!$G$20:$G$168,MATCH($C49,Insumos!$A$20:$A$168,0)),0) -> 14.9 | I49: =G49*H49 -> 0.076020408
A50: massa-mini-pizza | B50: Massa Mini Pizza | C50: acucar-demerara | D50: Açucar Demerara | E50: 0.01 | F50: =IFERROR(INDEX(Insumos!$F$4:$F$168,MATCH($C50,Insumos!$A$4:$A$168,0)),1) -> 0.98 | G50: =IFERROR(E50/F50,0) -> 0.010204082 | H50: =IFERROR(INDEX(Insumos!$G$20:$G$168,MATCH($C50,Insumos!$A$20:$A$168,0)),0) -> 6 | I50: =G50*H50 -> 0.06122449
A51: massa-mini-pizza | B51: Massa Mini Pizza | C51: sal-integral | D51: Sal Integral | E51: 0.005 | F51: =IFERROR(INDEX(Insumos!$F$4:$F$168,MATCH($C51,Insumos!$A$4:$A$168,0)),1) -> 0.98 | G51: =IFERROR(E51/F51,0) -> 0.0051020408 | H51: =IFERROR(INDEX(Insumos!$G$20:$G$168,MATCH($C51,Insumos!$A$20:$A$168,0)),0) -> 5 | I51: =G51*H51 -> 0.025510204
A52: massa-mini-pizza | B52: Massa Mini Pizza | C52: ovos | D52: Ovos | E52: 0.05 | F52: =IFERROR(INDEX(Insumos!$F$4:$F$168,MATCH($C52,Insumos!$A$4:$A$168,0)),1) -> 1 | G52: =IFERROR(E52/F52,0) -> 0.05 | H52: =IFERROR(INDEX(Insumos!$G$20:$G$168,MATCH($C52,Insumos!$A$20:$A$168,0)),0) -> 15 | I52: =G52*H52 -> 0.75
A53: massa-mini-pizza | B53: Massa Mini Pizza | C53: psyllium | D53: Psyllium | E53: 0.01 | F53: =IFERROR(INDEX(Insumos!$F$4:$F$168,MATCH($C53,Insumos!$A$4:$A$168,0)),1) -> 0.98 | G53: =IFERROR(E53/F53,0) -> 0.010204082 | H53: =IFERROR(INDEX(Insumos!$G$20:$G$168,MATCH($C53,Insumos!$A$20:$A$168,0)),0) -> 54.4 | I53: =G53*H53 -> 0.55510204
A54: massa-mini-pizza | B54: Massa Mini Pizza | C54: azeite-de-oliva | D54: Azeite de Oliva | E54: 0.01 | F54: =IFERROR(INDEX(Insumos!$F$4:$F$168,MATCH($C54,Insumos!$A$4:$A$168,0)),1) -> 0.95 | G54: =IFERROR(E54/F54,0) -> 0.010526316 | H54: =IFERROR(INDEX(Insumos!$G$20:$G$168,MATCH($C54,Insumos!$A$20:$A$168,0)),0) -> 20 | I54: =G54*H54 -> 0.21052632
A55: massa-mini-pizza | B55: Massa Mini Pizza | C55: agua | D55: Água | E55: 0.075 | F55: =IFERROR(INDEX(Insumos!$F$4:$F$168,MATCH($C55,Insumos!$A$4:$A$168,0)),1) -> 0.98 | G55: =IFERROR(E55/F55,0) -> 0.076530612 | H55: =IFERROR(INDEX(Insumos!$G$20:$G$168,MATCH($C55,Insumos!$A$20:$A$168,0)),0) -> 1.5 | I55: =G55*H55 -> 0.11479592
A56: massa-mini-pizza | B56: Massa Mini Pizza | C56: molho-de-tomate | D56: Molho de Tomate | E56: 0.05 | F56: =IFERROR(INDEX(Insumos!$F$4:$F$168,MATCH($C56,Insumos!$A$4:$A$168,0)),1) -> 0.98 | G56: =IFERROR(E56/F56,0) -> 0.051020408 | H56: =IFERROR(INDEX(Insumos!$G$20:$G$168,MATCH($C56,Insumos!$A$20:$A$168,0)),0) -> 11.3219 | I56: =G56*H56 -> 0.57764796
A57: pao-de-mandioquinha | B57: Pão de Mandioquinha | C57: mandioquinha | D57: Mandioquinha | E57: 1 | F57: =IFERROR(INDEX(Insumos!$F$4:$F$168,MATCH($C57,Insumos!$A$4:$A$168,0)),1) -> 0.75 | G57: =IFERROR(E57/F57,0) -> 1.3333333 | H57: =IFERROR(INDEX(Insumos!$G$20:$G$168,MATCH($C57,Insumos!$A$20:$A$168,0)),0) -> 11.9 | I57: =G57*H57 -> 15.866667
A58: pao-de-mandioquinha | B58: Pão de Mandioquinha | C58: polvilho-doce | D58: Polvilho Doce | E58: 0.6 | F58: =IFERROR(INDEX(Insumos!$F$4:$F$168,MATCH($C58,Insumos!$A$4:$A$168,0)),1) -> 0.98 | G58: =IFERROR(E58/F58,0) -> 0.6122449 | H58: =IFERROR(INDEX(Insumos!$G$20:$G$168,MATCH($C58,Insumos!$A$20:$A$168,0)),0) -> 12 | I58: =G58*H58 -> 7.3469388
A59: pao-de-mandioquinha | B59: Pão de Mandioquinha | C59: polvilho-azedo | D59: Polvilho Azedo | E59: 0.4 | F59: =IFERROR(INDEX(Insumos!$F$4:$F$168,MATCH($C59,Insumos!$A$4:$A$168,0)),1) -> 0.98 | G59: =IFERROR(E59/F59,0) -> 0.40816327 | H59: =IFERROR(INDEX(Insumos!$G$20:$G$168,MATCH($C59,Insumos!$A$20:$A$168,0)),0) -> 5 | I59: =G59*H59 -> 2.0408163
... A66: quiche-de-brocolis | B66: Quiche de Brócolis | C66: alho-poro | D66: Alho-poró | E66: 0.1 | F66: =IFERROR(INDEX(Insumos!$F$4:$F$168,MATCH($C66,Insumos!$A$4:$A$168,0)),1) -> 0.9 | G66: =IFERROR(E66/F66,0) -> 0.11111111 | H66: =IFERROR(INDEX(Insumos!$G$20:$G$168,MATCH($C66,Insumos!$A$20:$A$168,0)),0) -> 50 | I66: =G66*H66 -> 5.5555556
A67: quiche-de-brocolis | B67: Quiche de Brócolis | C67: creme-de-castanha | D67: Creme de Castanha | E67: 0.5 | F67: =IFERROR(INDEX(Insumos!$F$4:$F$168,MATCH($C67,Insumos!$A$4:$A$168,0)),1) -> 1 | G67: =IFERROR(E67/F67,0) -> 0.5 | H67: =Insumos!$G$4 -> 27.661974 | I67: =G67*H67 -> 13.830987
A68: quiche-de-brocolis | B68: Quiche de Brócolis | C68: brocolis | D68: Brócolis | E68: 0.4 | F68: =IFERROR(INDEX(Insumos!$F$4:$F$168,MATCH($C68,Insumos!$A$4:$A$168,0)),1) -> 0.95 | G68: =IFERROR(E68/F68,0) -> 0.42105263 | H68: =IFERROR(INDEX(Insumos!$G$20:$G$168,MATCH($C68,Insumos!$A$20:$A$168,0)),0) -> 30 | I68: =G68*H68 -> 12.631579
A69: quiche-de-frango | B69: Quiche de Frango | C69: massa-para-quiche | D69: Massa para Quiche | E69: 0.6 | F69: =IFERROR(INDEX(Insumos!$F$4:$F$168,MATCH($C69,Insumos!$A$4:$A$168,0)),1) -> 0.98 | G69: =IFERROR(E69/F69,0) -> 0.6122449 | H69: =IFERROR(INDEX(Insumos!$G$20:$G$168,MATCH($C69,Insumos!$A$20:$A$168,0)),0) -> 14.0501 | I69: =G69*H69 -> 8.602102
A70: quiche-de-frango | B70: Quiche de Frango | C70: frango-desfiado-com-molho-de-tomate | D70: Frango Desfiado com Molho de Tomate | E70: 0.3 | F70: =IFERROR(INDEX(Insumos!$F$4:$F$168,MATCH($C70,Insumos!$A$4:$A$168,0)),1) -> 1 | G70: =IFERROR(E70/F70,0) -> 0.3 | H70: =Insumos!$G$7 -> 34.885912 | I70: =G70*H70 -> 10.465773
A71: quiche-de-frango | B71: Quiche de Frango | C71: creme-de-castanha | D71: Creme de Castanha | E71: 0.5 | F71: =IFERROR(INDEX(Insumos!$F$4:$F$168,MATCH($C71,Insumos!$A$4:$A$168,0)),1) -> 1 | G71: =IFERROR(E71/F71,0) -> 0.5 | H71: =Insumos!$G$4 -> 27.661974 | I71: =G71*H71 -> 13.830987
A72: quiche-de-frango | B72: Quiche de Frango | C72: brocolis | D72: Brócolis | E72: 0.2 | F72: =IFERROR(INDEX(Insumos!$F$4:$F$168,MATCH($C72,Insumos!$A$4:$A$168,0)),1) -> 0.95 | G72: =IFERROR(E72/F72,0) -> 0.21052632 | H72: =IFERROR(INDEX(Insumos!$G$20:$G$168,MATCH($C72,Insumos!$A$20:$A$168,0)),0) -> 30 | I72: =G72*H72 -> 6.3157895
A73: sanduba-de-frango | B73: Sanduba de Pao-nobis, Frango e Requeiju | C73: creme-de-castanha | D73: Creme de Castanha | E73: 0.01 | F73: =IFERROR(INDEX(Insumos!$F$4:$F$168,MATCH($C73,Insumos!$A$4:$A$168,0)),1) -> 1 | G73: =IFERROR(E73/F73,0) -> 0.01 | H73: =Insumos!$G$4 -> 27.661974 | I73: =G73*H73 -> 0.27661974
A74: sanduba-de-frango | B74: Sanduba de Pao-nobis, Frango e Requeiju | C74: pao-para-sanduiche | D74: Pão-para Sanduiche | E74: 1 | F74: =IFERROR(INDEX(Insumos!$F$4:$F$168,MATCH($C74,Insumos!$A$4:$A$168,0)),1) -> 1 | G74: =IFERROR(E74/F74,0) -> 1 | H74: =IFERROR(INDEX(Insumos!$G$20:$G$168,MATCH($C74,Insumos!$A$20:$A$168,0)),0) -> 1.1125 | I74: =G74*H74 -> 1.1125
A75: sanduba-de-frango | B75: Sanduba de Pao-nobis, Frango e Requeiju | C75: frango-desfiado-com-molho-de-tomate | D75: Frango Desfiado com Molho de Tomate | E75: 0.05 | F75: =IFERROR(INDEX(Insumos!$F$4:$F$168,MATCH($C75,Insumos!$A$4:$A$168,0)),1) -> 1 | G75: =IFERROR(E75/F75,0) -> 0.05 | H75: =Insumos!$G$7 -> 34.885912 | I75: =G75*H75 -> 1.7442956
A76: sanduba-de-frango | B76: Sanduba de Pao-nobis, Frango e Requeiju | C76: alface | D76: Alface | E76: 0.02 | F76: =IFERROR(INDEX(Insumos!$F$4:$F$168,MATCH($C76,Insumos!$A$4:$A$168,0)),1) -> 0.79 | G76: =IFERROR(E76/F76,0) -> 0.025316456 | H76: =IFERROR(INDEX(Insumos!$G$20:$G$168,MATCH($C76,Insumos!$A$20:$A$168,0)),0) -> 5 | I76: =G76*H76 -> 0.12658228
A77: sanduba-de-frango | B77: Sanduba de Pao-nobis, Frango e Requeiju | C77: tomate-para-sanduba | D77: Tomate para Sanduba | E77: 0.015 | F77: =IFERROR(INDEX(Insumos!$F$4:$F$168,MATCH($C77,Insumos!$A$4:$A$168,0)),1) -> 1 | G77: =IFERROR(E77/F77,0) -> 0.015 | H77: =IFERROR(INDEX(Insumos!$G$20:$G$168,MATCH($C77,Insumos!$A$20:$A$168,0)),0) -> 6 | I77: =G77*H77 -> 0.09
A78: torta-salgada-de-frango | B78: Torta Salgada de Frango | C78: ovos | D78: Ovos | E78: 0.2 | F78: =IFERROR(INDEX(Insumos!$F$4:$F$168,MATCH($C78,Insumos!$A$4:$A$168,0)),1) -> 1 | G78: =IFERROR(E78/F78,0) -> 0.2 | H78: =IFERROR(INDEX(Insumos!$G$20:$G$168,MATCH($C78,Insumos!$A$20:$A$168,0)),0) -> 15 | I78: =G78*H78 -> 3
A79: torta-salgada-de-frango | B79: Torta Salgada de Frango | C79: farinha-de-arroz | D79: Farinha de Arroz | E79: 0.15 | F79: =IFERROR(INDEX(Insumos!$F$4:$F$168,MATCH($C79,Insumos!$A$4:$A$168,0)),1) -> 0.98 | G79: =IFERROR(E79/F79,0) -> 0.15306122 | H79: =IFERROR(INDEX(Insumos!$G$20:$G$168,MATCH($C79,Insumos!$A$20:$A$168,0)),0) -> 7.49 | I79: =G79*H79 -> 1.1464286
A80: torta-salgada-de-frango | B80: Torta Salgada de Frango | C80: agua | D80: Água | E80: 0.15 | F80: =IFERROR(INDEX(Insumos!$F$4:$F$168,MATCH($C80,Insumos!$A$4:$A$168,0)),1) -> 0.98 | G80: =IFERROR(E80/F80,0) -> 0.15306122 | H80: =IFERROR(INDEX(Insumos!$G$20:$G$168,MATCH($C80,Insumos!$A$20:$A$168,0)),0) -> 1.5 | I80: =G80*H80 -> 0.22959184
A81: torta-salgada-de-frango | B81: Torta Salgada de Frango | C81: fermento-quimico | D81: Fermento Químico | E81: 0.01 | F81: =IFERROR(INDEX(Insumos!$F$4:$F$168,MATCH($C81,Insumos!$A$4:$A$168,0)),1) -> 0.98 | G81: =IFERROR(E81/F81,0) -> 0.010204082 | H81: =IFERROR(INDEX(Insumos!$G$20:$G$168,MATCH($C81,Insumos!$A$20:$A$168,0)),0) -> 55.96 | I81: =G81*H81 -> 0.57102041
A82: torta-salgada-de-frango | B82: Torta Salgada de Frango | C82: frango-desfiado-com-molho-de-tomate | D82: Frango Desfiado com Molho de Tomate | E82: 0.35 | F82: =IFERROR(INDEX(Insumos!$F$4:$F$168,MATCH($C82,Insumos!$A$4:$A$168,0)),1) -> 1 | G82: =IFERROR(E82/F82,0) -> 0.35 | H82: =Insumos!$G$7 -> 34.885912 | I82: =G82*H82 -> 12.210069
A83: torta-salgada-de-frango | B83: Torta Salgada de Frango | C83: aveia | D83: Aveia | E83: 0.1 | F83: =IFERROR(INDEX(Insumos!$F$4:$F$168,MATCH($C83,Insumos!$A$4:$A$168,0)),1) -> 0.98 | G83: =IFERROR(E83/F83,0) -> 0.10204082 | H83: =IFERROR(INDEX(Insumos!$G$20:$G$168,MATCH($C83,Insumos!$A$20:$A$168,0)),0) -> 16.9 | I83: =G83*H83 -> 1.7244898
A84: torta-salgada-de-frango | B84: Torta Salgada de Frango | C84: sal-integral | D84: Sal Integral | E84: 0.005 | F84: =IFERROR(INDEX(Insumos!$F$4:$F$168,MATCH($C84,Insumos!$A$4:$A$168,0)),1) -> 0.98 | G84: =IFERROR(E84/F84,0) -> 0.0051020408 | H84: =IFERROR(INDEX(Insumos!$G$20:$G$168,MATCH($C84,Insumos!$A$20:$A$168,0)),0) -> 5 | I84: =G84*H84 -> 0.025510204
A85: torta-salgada-de-frango | B85: Torta Salgada de Frango | C85: azeite-de-oliva | D85: Azeite de Oliva | E85: 0.075 | F85: =IFERROR(INDEX(Insumos!$F$4:$F$168,MATCH($C85,Insumos!$A$4:$A$168,0)),1) -> 0.95 | G85: =IFERROR(E85/F85,0) -> 0.078947368 | H85: =IFERROR(INDEX(Insumos!$G$20:$G$168,MATCH($C85,Insumos!$A$20:$A$168,0)),0) -> 20 | I85: =G85*H85 -> 1.5789474
A86: batida-nuts | B86: Batida de Nuts | C86: pasta-de-amendoim | D86: Pasta de Amendoim | E86: 0.01 | F86: =IFERROR(INDEX(Insumos!$F$4:$F$168,MATCH($C86,Insumos!$A$4:$A$168,0)),1) -> 0.98 | G86: =IFERROR(E86/F86,0) -> 0.010204082 | H86: =IFERROR(INDEX(Insumos!$G$20:$G$168,MATCH($C86,Insumos!$A$20:$A$168,0)),0) -> 30 | I86: =G86*H86 -> 0.30612245
A87: batida-nuts | B87: Batida de Nuts | C87: agua | D87: Água | E87: 0.1 | F87: =IFERROR(INDEX(Insumos!$F$4:$F$168,MATCH($C87,Insumos!$A$4:$A$168,0)),1) -> 0.98 | G87: =IFERROR(E87/F87,0) -> 0.10204082 | H87: =IFERROR(INDEX(Insumos!$G$20:$G$168,MATCH($C87,Insumos!$A$20:$A$168,0)),0) -> 1.5 | I87: =G87*H87 -> 0.15306122
A88: batida-nuts | B88: Batida de Nuts | C88: canela-em-po | D88: Canela em Pó | E88: 0.001 | F88: =IFERROR(INDEX(Insumos!$F$4:$F$168,MATCH($C88,Insumos!$A$4:$A$168,0)),1) -> 0.98 | G88: =IFERROR(E88/F88,0) -> 0.0010204082 | H88: =IFERROR(INDEX(Insumos!$G$20:$G$168,MATCH($C88,Insumos!$A$20:$A$168,0)),0) -> 27 | I88: =G88*H88 -> 0.02755102
A89: batida-nuts | B89: Batida de Nuts | C89: aveia | D89: Aveia | E89: 0.015 | F89: =IFERROR(INDEX(Insumos!$F$4:$F$168,MATCH($C89,Insumos!$A$4:$A$168,0)),1) -> 0.98 | G89: =IFERROR(E89/F89,0) -> 0.015306122 | H89: =IFERROR(INDEX(Insumos!$G$20:$G$168,MATCH($C89,Insumos!$A$20:$A$168,0)),0) -> 16.9 | I89: =G89*H89 -> 0.25867347
A90: batida-nuts | B90: Batida de Nuts | C90: banana-sem-casca | D90: Banana sem Casca | E90: 0.1 | F90: =IFERROR(INDEX(Insumos!$F$4:$F$168,MATCH($C90,Insumos!$A$4:$A$168,0)),1) -> 0.62 | G90: =IFERROR(E90/F90,0) -> 0.16129032 | H90: =IFERROR(INDEX(Insumos!$G$20:$G$168,MATCH($C90,Insumos!$A$20:$A$168,0)),0) -> 10 | I90: =G90*H90 -> 1.6129032
A91: creme-de-castanha | B91: Catupiry de Castanha | C91: castanha-de-caju | D91: Castanha de Caju | E91: 0.2 | F91: =IFERROR(INDEX(Insumos!$F$4:$F$168,MATCH($C91,Insumos!$A$4:$A$168,0)),1) -> 0.98 | G91: =IFERROR(E91/F91,0) -> 0.20408163 | H91: =IFERROR(INDEX(Insumos!$G$20:$G$168,MATCH($C91,Insumos!$A$20:$A$168,0)),0) -> 69.9 | I91: =G91*H91 -> 14.265306
A92: creme-de-castanha | B92: Catupiry de Castanha | C92: agua | D92: Água | E92: 0.4 | F92: =IFERROR(INDEX(Insumos!$F$4:$F$168,MATCH($C92,Insumos!$A$4:$A$168,0)),1) -> 0.98 | G92: =IFERROR(E92/F92,0) -> 0.40816327 | H92: =IFERROR(INDEX(Insumos!$G$20:$G$168,MATCH($C92,Insumos!$A$20:$A$168,0)),0) -> 1.5 | I92: =G92*H92 -> 0.6122449
A93: creme-de-castanha | B93: Catupiry de Castanha | C93: levedura-nutricional | D93: Levedura Nutricional | E93: 0.015 | F93: =IFERROR(INDEX(Insumos!$F$4:$F$168,MATCH($C93,Insumos!$A$4:$A$168,0)),1) -> 0.98 | G93: =IFERROR(E93/F93,0) -> 0.015306122 | H93: =IFERROR(INDEX(Insumos!$G$20:$G$168,MATCH($C93,Insumos!$A$20:$A$168,0)),0) -> 149.9 | I93: =G93*H93 -> 2.2943878
A94: creme-de-castanha | B94: Catupiry de Castanha | C94: sal-integral | D94: Sal Integral | E94: 0.005 | F94: =IFERROR(INDEX(Insumos!$F$4:$F$168,MATCH($C94,Insumos!$A$4:$A$168,0)),1) -> 0.98 | G94: =IFERROR(E94/F94,0) -> 0.0051020408 | H94: =IFERROR(INDEX(Insumos!$G$20:$G$168,MATCH($C94,Insumos!$A$20:$A$168,0)),0) -> 5 | I94: =G94*H94 -> 0.025510204
A95: coxinha-de-festa | B95: Coxinha de Festa | C95: mix-sem-gluten-cris-gutierrez | D95: Mix sem Glúten Cris Gutierrez | E95: 0.15 | F95: =IFERROR(INDEX(Insumos!$F$4:$F$168,MATCH($C95,Insumos!$A$4:$A$168,0)),1) -> 0.98 | G95: =IFERROR(E95/F95,0) -> 0.15306122 | H95: =Insumos!$G$15 -> 10.219598 | I95: =G95*H95 -> 1.5642242
A96: coxinha-de-festa | B96: Coxinha de Festa | C96: pure-de-batatas | D96: Purê de Batatas | E96: 0.45 | F96: =IFERROR(INDEX(Insumos!$F$4:$F$168,MATCH($C96,Insumos!$A$4:$A$168,0)),1) -> 1 | G96: =IFERROR(E96/F96,0) -> 0.45 | H96: =Insumos!$G$16 -> 12.142728 | I96: =G96*H96 -> 5.4642276
A97: coxinha-de-festa | B97: Coxinha de Festa | C97: caldo-de-frango | D97: Caldo de Frango | E97: 0.2 | F97: =IFERROR(INDEX(Insumos!$F$4:$F$168,MATCH($C97,Insumos!$A$4:$A$168,0)),1) -> 0.98 | G97: =IFERROR(E97/F97,0) -> 0.20408163 | H97: =IFERROR(INDEX(Insumos!$G$20:$G$168,MATCH($C97,Insumos!$A$20:$A$168,0)),0) -> 10 | I97: =G97*H97 -> 2.0408163
A98: coxinha-de-festa | B98: Coxinha de Festa | C98: sal-integral | D98: Sal Integral | E98: 0.01 | F98: =IFERROR(INDEX(Insumos!$F$4:$F$168,MATCH($C98,Insumos!$A$4:$A$168,0)),1) -> 0.98 | G98: =IFERROR(E98/F98,0) -> 0.010204082 | H98: =IFERROR(INDEX(Insumos!$G$20:$G$168,MATCH($C98,Insumos!$A$20:$A$168,0)),0) -> 5 | I98: =G98*H98 -> 0.051020408
A99: coxinha-de-festa | B99: Coxinha de Festa | C99: azeite-de-oliva | D99: Azeite de Oliva | E99: 0.02 | F99: =IFERROR(INDEX(Insumos!$F$4:$F$168,MATCH($C99,Insumos!$A$4:$A$168,0)),1) -> 0.95 | G99: =IFERROR(E99/F99,0) -> 0.021052632 | H99: =IFERROR(INDEX(Insumos!$G$20:$G$168,MATCH($C99,Insumos!$A$20:$A$168,0)),0) -> 20 | I99: =G99*H99 -> 0.42105263
A100: croquete-de-batata-e-frango | B100: Croquete de Batata e Frango | C100: batata-asterix | D100: Batata Asterix | E100: 0.75 | F100: =IFERROR(INDEX(Insumos!$F$4:$F$168,MATCH($C100,Insumos!$A$4:$A$168,0)),1) -> 0.85 | G100: =IFERROR(E100/F100,0) -> 0.88235294 | H100: =IFERROR(INDEX(Insumos!$G$20:$G$168,MATCH($C100,Insumos!$A$20:$A$168,0)),0) -> 8 | I100: =G100*H100 -> 7.0588235
A101: croquete-de-batata-e-frango | B101: Croquete de Batata e Frango | C101: frango-desfiado | D101: Frango Desfiado | E101: 0.5 | F101: =IFERROR(INDEX(Insumos!$F$4:$F$168,MATCH($C101,Insumos!$A$4:$A$168,0)),1) -> 0.5 | G101: =IFERROR(E101/F101,0) -> 1 | H101: =Insumos!$G$6 -> 22.902943 | I101: =G101*H101 -> 22.902943
A102: croquete-de-batata-e-frango | B102: Croquete de Batata e Frango | C102: cebola-sem-casca | D102: Cebola sem Casca | E102: 0.15 | F102: =IFERROR(INDEX(Insumos!$F$4:$F$168,MATCH($C102,Insumos!$A$4:$A$168,0)),1) -> 0.84 | G102: =IFERROR(E102/F102,0) -> 0.17857143 | H102: =IFERROR(INDEX(Insumos!$G$20:$G$168,MATCH($C102,Insumos!$A$20:$A$168,0)),0) -> 6 | I102: =G102*H102 -> 1.0714286
A103: croquete-de-batata-e-frango | B103: Croquete de Batata e Frango | C103: alho-cru | D103: Alho Cru | E103: 0.005 | F103: =IFERROR(INDEX(Insumos!$F$4:$F$168,MATCH($C103,Insumos!$A$4:$A$168,0)),1) -> 0.88 | G103: =IFERROR(E103/F103,0) -> 0.0056818182 | H103: =IFERROR(INDEX(Insumos!$G$20:$G$168,MATCH($C103,Insumos!$A$20:$A$168,0)),0) -> 24.99 | I103: =G103*H103 -> 0.14198864
A104: croquete-de-batata-e-frango | B104: Croquete de Batata e Frango | C104: sal-integral | D104: Sal Integral | E104: 0.015 | F104: =IFERROR(INDEX(Insumos!$F$4:$F$168,MATCH($C104,Insumos!$A$4:$A$168,0)),1) -> 0.98 | G104: =IFERROR(E104/F104,0) -> 0.015306122 | H104: =IFERROR(INDEX(Insumos!$G$20:$G$168,MATCH($C104,Insumos!$A$20:$A$168,0)),0) -> 5 | I104: =G104*H104 -> 0.076530612
A105: croquete-de-batata-e-frango | B105: Croquete de Batata e Frango | C105: curry | D105: Curry | E105: 0.01 | F105: =IFERROR(INDEX(Insumos!$F$4:$F$168,MATCH($C105,Insumos!$A$4:$A$168,0)),1) -> 0.98 | G105: =IFERROR(E105/F105,0) -> 0.010204082 | H105: =IFERROR(INDEX(Insumos!$G$20:$G$168,MATCH($C105,Insumos!$A$20:$A$168,0)),0) -> 9.54 | I105: =G105*H105 -> 0.097346939
A106: croquete-de-batata-e-frango | B106: Croquete de Batata e Frango | C106: alecrim | D106: Alecrim | E106: 0.003 | F106: =IFERROR(INDEX(Insumos!$F$4:$F$168,MATCH($C106,Insumos!$A$4:$A$168,0)),1) -> 0.95 | G106: =IFERROR(E106/F106,0) -> 0.0031578947 | H106: =IFERROR(INDEX(Insumos!$G$20:$G$168,MATCH($C106,Insumos!$A$20:$A$168,0)),0) -> 10 | I106: =G106*H106 -> 0.031578947
A107: croquete-de-batata-e-frango | B107: Croquete de Batata e Frango | C107: louro | D107: Louro | E107: 0.003 | F107: =IFERROR(INDEX(Insumos!$F$4:$F$168,MATCH($C107,Insumos!$A$4:$A$168,0)),1) -> 0.98 | G107: =IFERROR(E107/F107,0) -> 0.0030612245 | H107: =IFERROR(INDEX(Insumos!$G$20:$G$168,MATCH($C107,Insumos!$A$20:$A$168,0)),0) -> 44.55 | I107: =G107*H107 -> 0.13637755
A108: croquete-de-carne-e-cabotia | B108: Croquete de Batata e Frango | C108: abobora-cabotia | D108: Abobora Cabotia | E108: 0.3 | F108: =IFERROR(INDEX(Insumos!$F$4:$F$168,MATCH($C108,Insumos!$A$4:$A$168,0)),1) -> 0.97 | G108: =IFERROR(E108/F108,0) -> 0.30927835 | H108: =IFERROR(INDEX(Insumos!$G$20:$G$168,MATCH($C108,Insumos!$A$20:$A$168,0)),0) -> 6 | I108: =G108*H108 -> 1.8556701
A109: croquete-de-carne-e-cabotia | B109: Croquete de Batata e Frango | C109: carne-moida | D109: Carne Moida | E109: 0.6 | F109: =IFERROR(INDEX(Insumos!$F$4:$F$168,MATCH($C109,Insumos!$A$4:$A$168,0)),1) -> 0.95 | G109: =IFERROR(E109/F109,0) -> 0.63157895 | H109: =IFERROR(INDEX(Insumos!$G$20:$G$168,MATCH($C109,Insumos!$A$20:$A$168,0)),0) -> 60 | I109: =G109*H109 -> 37.894737
A110: croquete-de-carne-e-cabotia | B110: Croquete de Batata e Frango | C110: cebola-sem-casca | D110: Cebola sem Casca | E110: 0.15 | F110: =IFERROR(INDEX(Insumos!$F$4:$F$168,MATCH($C110,Insumos!$A$4:$A$168,0)),1) -> 0.84 | G110: =IFERROR(E110/F110,0) -> 0.17857143 | H110: =IFERROR(INDEX(Insumos!$G$20:$G$168,MATCH($C110,Insumos!$A$20:$A$168,0)),0) -> 6 | I110: =G110*H110 -> 1.0714286
A111: croquete-de-carne-e-cabotia | B111: Croquete de Batata e Frango | C111: alho-cru | D111: Alho Cru | E111: 0.005 | F111: =IFERROR(INDEX(Insumos!$F$4:$F$168,MATCH($C111,Insumos!$A$4:$A$168,0)),1) -> 0.88 | G111: =IFERROR(E111/F111,0) -> 0.0056818182 | H111: =IFERROR(INDEX(Insumos!$G$20:$G$168,MATCH($C111,Insumos!$A$20:$A$168,0)),0) -> 24.99 | I111: =G111*H111 -> 0.14198864
...

Sheet Conferência
A1: Conferência
A2: Compara o que esta planilha calcula com o que a sua planilha antiga calculava. Serve para você conferir se a migração ficou certa.
A3: O que foi conferido | B3: Valor | C3: O que isso quer dizer
A4: Receitas na planilha | B4: =COUNTA(Produtos!$A$4:$A$76) -> 73 | C4: Cada receita sua virou uma linha na aba Produtos.
A5: Receitas que a planilha antiga também calculava | B5: =COUNTIF(Produtos!$O$4:$O$76,">0") -> 73 | C5: Só estas dá para comparar. As outras a planilha antiga não trazia o custo por porção.
A6: Receitas com o mesmo custo (diferença abaixo de 1 centavo) | B6: =SUMPRODUCT((Produtos!$O$4:$O$76>0)*(ABS(Produtos!$P$4:$P$76)<0.01)) -> 45 | C6: Estas bateram exatamente com a sua planilha.
A7: Receitas com custo diferente | B7: =SUMPRODUCT((Produtos!$O$4:$O$76>0)*(ABS(Produtos!$P$4:$P$76)>=0.01)) -> 28 | C7: Veja a lista abaixo. Em geral é o alho-poró, explicado no documento que acompanha.
A8: Maior diferença para cima | B8: =MAX(Produtos!$P$4:$P$76) -> 7.3351373 | C8: Quanto o maior custo subiu em relação à planilha antiga.
A9: Maior diferença para baixo | B9: =MIN(Produtos!$P$4:$P$76) -> -0.22019212 | C9: Quanto o maior custo caiu em relação à planilha antiga.
A10: Insumos cadastrados | B10: =COUNTA(Insumos!$A$4:$A$168) -> 165 | C10: Tudo que entra em alguma receita.
A11: Insumos sem preço | B11: =COUNTIF(Insumos!$G$20:$G$168,0) -> 0 | C11: Se aparecer algum, o custo das receitas que o usam está baixo demais.
A12: Insumos sem data de cotação | B12: =COUNTBLANK(Insumos!$I$20:$I$168) -> 149 | C12: Preencher ajuda a saber quando o preço envelheceu.
A15: Receitas em que o custo mudou
A16: Produto | B16: Custo agora | C16: Custo antes
A17: =IF(ABS(Produtos!$P$4)<0.01,"",Produtos!$B$4) -> Caldo de Batata Doce | B17: =IF(ABS(Produtos!$P$4)<0.01,"",Produtos!$K$4) -> 5.388183 | C17: =IF(ABS(Produtos!$P$4)<0.01,"",Produtos!$O$4) -> 5.3232
A18: =IF(ABS(Produtos!$P$5)<0.01,"",Produtos!$B$5) -> Caldo de Cabotia | B18: =IF(ABS(Produtos!$P$5)<0.01,"",Produtos!$K$5) -> 5.3415447 | C18: =IF(ABS(Produtos!$P$5)<0.01,"",Produtos!$O$5) -> 5.2765
A19: =IF(ABS(Produtos!$P$6)<0.01,"",Produtos!$B$6) -> Caldo de Legumes e Frango | B19: =IF(ABS(Produtos!$P$6)<0.01,"",Produtos!$K$6) -> 6.1683871 | C19: =IF(ABS(Produtos!$P$6)<0.01,"",Produtos!$O$6) -> 6.1034
A20: =IF(ABS(Produtos!$P$7)<0.01,"",Produtos!$B$7) -> Coxinha Massa Trad | B20: =IF(ABS(Produtos!$P$7)<0.01,"",Produtos!$K$7) -> 3.6098718 | C20: =IF(ABS(Produtos!$P$7)<0.01,"",Produtos!$O$7) -> 3.5749
A21: =IF(ABS(Produtos!$P$8)<0.01,"",Produtos!$B$8) | B21: =IF(ABS(Produtos!$P$8)<0.01,"",Produtos!$K$8) | C21: =IF(ABS(Produtos!$P$8)<0.01,"",Produtos!$O$8)
A22: =IF(ABS(Produtos!$P$9)<0.01,"",Produtos!$B$9) -> Esfira de Carne | B22: =IF(ABS(Produtos!$P$9)<0.01,"",Produtos!$K$9) -> 6.06824 | C22: =IF(ABS(Produtos!$P$9)<0.01,"",Produtos!$O$9) -> 6.1932
A23: =IF(ABS(Produtos!$P$10)<0.01,"",Produtos!$B$10) | B23: =IF(ABS(Produtos!$P$10)<0.01,"",Produtos!$K$10) | C23: =IF(ABS(Produtos!$P$10)<0.01,"",Produtos!$O$10)
A24: =IF(ABS(Produtos!$P$11)<0.01,"",Produtos!$B$11) | B24: =IF(ABS(Produtos!$P$11)<0.01,"",Produtos!$K$11) | C24: =IF(ABS(Produtos!$P$11)<0.01,"",Produtos!$O$11)
A25: =IF(ABS(Produtos!$P$12)<0.01,"",Produtos!$B$12) -> Quiche de Brócolis | B25: =IF(ABS(Produtos!$P$12)<0.01,"",Produtos!$K$12) -> 4.0620223 | C25: =IF(ABS(Produtos!$P$12)<0.01,"",Produtos!$O$12) -> 3.9601
A26: =IF(ABS(Produtos!$P$13)<0.01,"",Produtos!$B$13) | B26: =IF(ABS(Produtos!$P$13)<0.01,"",Produtos!$K$13) | C26: =IF(ABS(Produtos!$P$13)<0.01,"",Produtos!$O$13)
A27: =IF(ABS(Produtos!$P$14)<0.01,"",Produtos!$B$14) -> Sanduba de Pao-nobis, Frango e Requeiju | B27: =IF(ABS(Produtos!$P$14)<0.01,"",Produtos!$K$14) -> 3.3499976 | C27: =IF(ABS(Produtos!$P$14)<0.01,"",Produtos!$O$14) -> 3.3114
A28: =IF(ABS(Produtos!$P$15)<0.01,"",Produtos!$B$15) -> Torta Salgada de Frango | B28: =IF(ABS(Produtos!$P$15)<0.01,"",Produtos!$K$15) -> 2.9265796 | C28: =IF(ABS(Produtos!$P$15)<0.01,"",Produtos!$O$15) -> 2.8823
A29: =IF(ABS(Produtos!$P$16)<0.01,"",Produtos!$B$16) | B29: =IF(ABS(Produtos!$P$16)<0.01,"",Produtos!$K$16) | C29: =IF(ABS(Produtos!$P$16)<0.01,"",Produtos!$O$16)
A30: =IF(ABS(Produtos!$P$17)<0.01,"",Produtos!$B$17) | B30: =IF(ABS(Produtos!$P$17)<0.01,"",Produtos!$K$17) | C30: =IF(ABS(Produtos!$P$17)<0.01,"",Produtos!$O$17)
A31: =IF(ABS(Produtos!$P$18)<0.01,"",Produtos!$B$18) | B31: =IF(ABS(Produtos!$P$18)<0.01,"",Produtos!$K$18) | C31: =IF(ABS(Produtos!$P$18)<0.01,"",Produtos!$O$18)
A32: =IF(ABS(Produtos!$P$19)<0.01,"",Produtos!$B$19) -> Croquete de Batata e Frango | B32: =IF(ABS(Produtos!$P$19)<0.01,"",Produtos!$K$19) -> 3.1517018 | C32: =IF(ABS(Produtos!$P$19)<0.01,"",Produtos!$O$19) -> 3.0867
A33: =IF(ABS(Produtos!$P$20)<0.01,"",Produtos!$B$20) | B33: =IF(ABS(Produtos!$P$20)<0.01,"",Produtos!$K$20) | C33: =IF(ABS(Produtos!$P$20)<0.01,"",Produtos!$O$20)
A34: =IF(ABS(Produtos!$P$21)<0.01,"",Produtos!$B$21) -> Empada de Frango | B34: =IF(ABS(Produtos!$P$21)<0.01,"",Produtos!$K$21) -> 1.9486759 | C34: =IF(ABS(Produtos!$P$21)<0.01,"",Produtos!$O$21) -> 1.36
A35: =IF(ABS(Produtos!$P$22)<0.01,"",Produtos!$B$22) -> Empadinha Veg | B35: =IF(ABS(Produtos!$P$22)<0.01,"",Produtos!$K$22) -> 0.42311712 | C35: =IF(ABS(Produtos!$P$22)<0.01,"",Produtos!$O$22) -> 0.1421
A36: =IF(ABS(Produtos!$P$23)<0.01,"",Produtos!$B$23) -> Empadinha de Carne | B36: =IF(ABS(Produtos!$P$23)<0.01,"",Produtos!$K$23) -> 0.88673673 | C36: =IF(ABS(Produtos!$P$23)<0.01,"",Produtos!$O$23) -> 0.899
A37: =IF(ABS(Produtos!$P$24)<0.01,"",Produtos!$B$24) | B37: =IF(ABS(Produtos!$P$24)<0.01,"",Produtos!$K$24) | C37: =IF(ABS(Produtos!$P$24)<0.01,"",Produtos!$O$24)
A38: =IF(ABS(Produtos!$P$25)<0.01,"",Produtos!$B$25) -> Escondidinho de Carne | B38: =IF(ABS(Produtos!$P$25)<0.01,"",Produtos!$K$25) -> 12.204508 | C38: =IF(ABS(Produtos!$P$25)<0.01,"",Produtos!$O$25) -> 12.4247
A39: =IF(ABS(Produtos!$P$26)<0.01,"",Produtos!$B$26) -> Escondidinho de Carne | B39: =IF(ABS(Produtos!$P$26)<0.01,"",Produtos!$K$26) -> 8.4373946 | C39: =IF(ABS(Produtos!$P$26)<0.01,"",Produtos!$O$26) -> 8.3411
A40: =IF(ABS(Produtos!$P$27)<0.01,"",Produtos!$B$27) | B40: =IF(ABS(Produtos!$P$27)<0.01,"",Produtos!$K$27) | C40: =IF(ABS(Produtos!$P$27)<0.01,"",Produtos!$O$27)
A41: =IF(ABS(Produtos!$P$28)<0.01,"",Produtos!$B$28) -> Frango Desfiado | B41: =IF(ABS(Produtos!$P$28)<0.01,"",Produtos!$K$28) -> 22.902943 | C41: =IF(ABS(Produtos!$P$28)<0.01,"",Produtos!$O$28) -> 22.2528
A42: =IF(ABS(Produtos!$P$29)<0.01,"",Produtos!$B$29) -> Frango Desfiado com Molho de Tomate | B42: =IF(ABS(Produtos!$P$29)<0.01,"",Produtos!$K$29) -> 54.742973 | C42: =IF(ABS(Produtos!$P$29)<0.01,"",Produtos!$O$29) -> 53.353
A43: =IF(ABS(Produtos!$P$30)<0.01,"",Produtos!$B$30) -> Frango com Molho Chuchu e Molho Branco e Arroz com Sementes | B43: =IF(ABS(Produtos!$P$30)<0.01,"",Produtos!$K$30) -> 4.5465119 | C43: =IF(ABS(Produtos!$P$30)<0.01,"",Produtos!$O$30) -> 4.5831
A44: =IF(ABS(Produtos!$P$31)<0.01,"",Produtos!$B$31) | B44: =IF(ABS(Produtos!$P$31)<0.01,"",Produtos!$K$31) | C44: =IF(ABS(Produtos!$P$31)<0.01,"",Produtos!$O$31)
A45: =IF(ABS(Produtos!$P$32)<0.01,"",Produtos!$B$32) | B45: =IF(ABS(Produtos!$P$32)<0.01,"",Produtos!$K$32) | C45: =IF(ABS(Produtos!$P$32)<0.01,"",Produtos!$O$32)
A46: =IF(ABS(Produtos!$P$33)<0.01,"",Produtos!$B$33) | B46: =IF(ABS(Produtos!$P$33)<0.01,"",Produtos!$K$33) | C46: =IF(ABS(Produtos!$P$33)<0.01,"",Produtos!$O$33)
A47: =IF(ABS(Produtos!$P$34)<0.01,"",Produtos!$B$34) | B47: =IF(ABS(Produtos!$P$34)<0.01,"",Produtos!$K$34) | C47: =IF(ABS(Produtos!$P$34)<0.01,"",Produtos!$O$34)
A48: =IF(ABS(Produtos!$P$35)<0.01,"",Produtos!$B$35) | B48: =IF(ABS(Produtos!$P$35)<0.01,"",Produtos!$K$35) | C48: =IF(ABS(Produtos!$P$35)<0.01,"",Produtos!$O$35)
A49: =IF(ABS(Produtos!$P$36)<0.01,"",Produtos!$B$36) | B49: =IF(ABS(Produtos!$P$36)<0.01,"",Produtos!$K$36) | C49: =IF(ABS(Produtos!$P$36)<0.01,"",Produtos!$O$36)
A50: =IF(ABS(Produtos!$P$37)<0.01,"",Produtos!$B$37) | B50: =IF(ABS(Produtos!$P$37)<0.01,"",Produtos!$K$37) | C50: =IF(ABS(Produtos!$P$37)<0.01,"",Produtos!$O$37)
A51: =IF(ABS(Produtos!$P$38)<0.01,"",Produtos!$B$38) | B51: =IF(ABS(Produtos!$P$38)<0.01,"",Produtos!$K$38) | C51: =IF(ABS(Produtos!$P$38)<0.01,"",Produtos!$O$38)
A52: =IF(ABS(Produtos!$P$39)<0.01,"",Produtos!$B$39) | B52: =IF(ABS(Produtos!$P$39)<0.01,"",Produtos!$K$39) | C52: =IF(ABS(Produtos!$P$39)<0.01,"",Produtos!$O$39)
A53: =IF(ABS(Produtos!$P$40)<0.01,"",Produtos!$B$40) | B53: =IF(ABS(Produtos!$P$40)<0.01,"",Produtos!$K$40) | C53: =IF(ABS(Produtos!$P$40)<0.01,"",Produtos!$O$40)
A54: =IF(ABS(Produtos!$P$41)<0.01,"",Produtos!$B$41) | B54: =IF(ABS(Produtos!$P$41)<0.01,"",Produtos!$K$41) | C54: =IF(ABS(Produtos!$P$41)<0.01,"",Produtos!$O$41)
A55: =IF(ABS(Produtos!$P$42)<0.01,"",Produtos!$B$42) -> Massa Low Carb para Quiche | B55: =IF(ABS(Produtos!$P$42)<0.01,"",Produtos!$K$42) -> 27.777737 | C55: =IF(ABS(Produtos!$P$42)<0.01,"",Produtos!$O$42) -> 20.4426
A56: =IF(ABS(Produtos!$P$43)<0.01,"",Produtos!$B$43) -> Massa de Esfira | B56: =IF(ABS(Produtos!$P$43)<0.01,"",Produtos!$K$43) -> 18.314411 | C56: =IF(ABS(Produtos!$P$43)<0.01,"",Produtos!$O$43) -> 18.3297
A57: =IF(ABS(Produtos!$P$44)<0.01,"",Produtos!$B$44) | B57: =IF(ABS(Produtos!$P$44)<0.01,"",Produtos!$K$44) | C57: =IF(ABS(Produtos!$P$44)<0.01,"",Produtos!$O$44)
A58: =IF(ABS(Produtos!$P$45)<0.01,"",Produtos!$B$45) | B58: =IF(ABS(Produtos!$P$45)<0.01,"",Produtos!$K$45) | C58: =IF(ABS(Produtos!$P$45)<0.01,"",Produtos!$O$45)
A59: =IF(ABS(Produtos!$P$46)<0.01,"",Produtos!$B$46) | B59: =IF(ABS(Produtos!$P$46)<0.01,"",Produtos!$K$46) | C59: =IF(ABS(Produtos!$P$46)<0.01,"",Produtos!$O$46)
A60: =IF(ABS(Produtos!$P$47)<0.01,"",Produtos!$B$47) | B60: =IF(ABS(Produtos!$P$47)<0.01,"",Produtos!$K$47) | C60: =IF(ABS(Produtos!$P$47)<0.01,"",Produtos!$O$47)
A61: =IF(ABS(Produtos!$P$48)<0.01,"",Produtos!$B$48) | B61: =IF(ABS(Produtos!$P$48)<0.01,"",Produtos!$K$48) | C61: =IF(ABS(Produtos!$P$48)<0.01,"",Produtos!$O$48)
A62: =IF(ABS(Produtos!$P$49)<0.01,"",Produtos!$B$49) | B62: =IF(ABS(Produtos!$P$49)<0.01,"",Produtos!$K$49) | C62: =IF(ABS(Produtos!$P$49)<0.01,"",Produtos!$O$49)
A63: =IF(ABS(Produtos!$P$50)<0.01,"",Produtos!$B$50) | B63: =IF(ABS(Produtos!$P$50)<0.01,"",Produtos!$K$50) | C63: =IF(ABS(Produtos!$P$50)<0.01,"",Produtos!$O$50)
A64: =IF(ABS(Produtos!$P$51)<0.01,"",Produtos!$B$51) | B64: =IF(ABS(Produtos!$P$51)<0.01,"",Produtos!$K$51) | C64: =IF(ABS(Produtos!$P$51)<0.01,"",Produtos!$O$51)
A65: =IF(ABS(Produtos!$P$52)<0.01,"",Produtos!$B$52) -> Pastelzinho de Festa | B65: =IF(ABS(Produtos!$P$52)<0.01,"",Produtos!$K$52) -> 0.89938022 | C65: =IF(ABS(Produtos!$P$52)<0.01,"",Produtos!$O$52) -> 0.9141
A66: =IF(ABS(Produtos!$P$53)<0.01,"",Produtos!$B$53) | B66: =IF(ABS(Produtos!$P$53)<0.01,"",Produtos!$K$53) | C66: =IF(ABS(Produtos!$P$53)<0.01,"",Produtos!$O$53)
A67: =IF(ABS(Produtos!$P$54)<0.01,"",Produtos!$B$54) -> Purê de Batatas | B67: =IF(ABS(Produtos!$P$54)<0.01,"",Produtos!$K$54) -> 12.142728 | C67: =IF(ABS(Produtos!$P$54)<0.01,"",Produtos!$O$54) -> 12.199
A68: =IF(ABS(Produtos!$P$55)<0.01,"",Produtos!$B$55) | B68: =IF(ABS(Produtos!$P$55)<0.01,"",Produtos!$K$55) | C68: =IF(ABS(Produtos!$P$55)<0.01,"",Produtos!$O$55)
A69: =IF(ABS(Produtos!$P$56)<0.01,"",Produtos!$B$56) | B69: =IF(ABS(Produtos!$P$56)<0.01,"",Produtos!$K$56) | C69: =IF(ABS(Produtos!$P$56)<0.01,"",Produtos!$O$56)
A70: =IF(ABS(Produtos!$P$57)<0.01,"",Produtos!$B$57) | B70: =IF(ABS(Produtos!$P$57)<0.01,"",Produtos!$K$57) | C70: =IF(ABS(Produtos!$P$57)<0.01,"",Produtos!$O$57)
A71: =IF(ABS(Produtos!$P$58)<0.01,"",Produtos!$B$58) | B71: =IF(ABS(Produtos!$P$58)<0.01,"",Produtos!$K$58) | C71: =IF(ABS(Produtos!$P$58)<0.01,"",Produtos!$O$58)
A72: =IF(ABS(Produtos!$P$59)<0.01,"",Produtos!$B$59) | B72: =IF(ABS(Produtos!$P$59)<0.01,"",Produtos!$K$59) | C72: =IF(ABS(Produtos!$P$59)<0.01,"",Produtos!$O$59)
A73: =IF(ABS(Produtos!$P$60)<0.01,"",Produtos!$B$60) | B73: =IF(ABS(Produtos!$P$60)<0.01,"",Produtos!$K$60) | C73: =IF(ABS(Produtos!$P$60)<0.01,"",Produtos!$O$60)
A74: =IF(ABS(Produtos!$P$61)<0.01,"",Produtos!$B$61) | B74: =IF(ABS(Produtos!$P$61)<0.01,"",Produtos!$K$61) | C74: =IF(ABS(Produtos!$P$61)<0.01,"",Produtos!$O$61)
A75: =IF(ABS(Produtos!$P$62)<0.01,"",Produtos!$B$62) | B75: =IF(ABS(Produtos!$P$62)<0.01,"",Produtos!$K$62) | C75: =IF(ABS(Produtos!$P$62)<0.01,"",Produtos!$O$62)
A76: =IF(ABS(Produtos!$P$63)<0.01,"",Produtos!$B$63) -> Pão de Sementes | B76: =IF(ABS(Produtos!$P$63)<0.01,"",Produtos!$K$63) -> 2.7130706 | C76: =IF(ABS(Produtos!$P$63)<0.01,"",Produtos!$O$63) -> 2.6939
A77: =IF(ABS(Produtos!$P$64)<0.01,"",Produtos!$B$64) | B77: =IF(ABS(Produtos!$P$64)<0.01,"",Produtos!$K$64) | C77: =IF(ABS(Produtos!$P$64)<0.01,"",Produtos!$O$64)
A78: =IF(ABS(Produtos!$P$65)<0.01,"",Produtos!$B$65) -> Quiche Ricota, Ora-pro-nóbis e Alho-poró | B78: =IF(ABS(Produtos!$P$65)<0.01,"",Produtos!$K$65) -> 4.7388895 | C78: =IF(ABS(Produtos!$P$65)<0.01,"",Produtos!$O$65) -> 3.8608
A79: =IF(ABS(Produtos!$P$66)<0.01,"",Produtos!$B$66) -> Quiche Ricota, Ora-pro-nóbis e Alho-poró | B79: =IF(ABS(Produtos!$P$66)<0.01,"",Produtos!$K$66) -> 3.8141423 | C79: =IF(ABS(Produtos!$P$66)<0.01,"",Produtos!$O$66) -> 2.4091
A80: =IF(ABS(Produtos!$P$67)<0.01,"",Produtos!$B$67) -> Quiche Ricota, Ora-pro-nóbis e Alho-poró | B80: =IF(ABS(Produtos!$P$67)<0.01,"",Produtos!$K$67) -> 3.3383725 | C80: =IF(ABS(Produtos!$P$67)<0.01,"",Produtos!$O$67) -> 2.2846
A81: =IF(ABS(Produtos!$P$68)<0.01,"",Produtos!$B$68) -> Quiche Ricota, Ora-pro-nóbis e Espinafre | B81: =IF(ABS(Produtos!$P$68)<0.01,"",Produtos!$K$68) -> 1.8105103 | C81: =IF(ABS(Produtos!$P$68)<0.01,"",Produtos!$O$68) -> 1.108
A82: =IF(ABS(Produtos!$P$69)<0.01,"",Produtos!$B$69) | B82: =IF(ABS(Produtos!$P$69)<0.01,"",Produtos!$K$69) | C82: =IF(ABS(Produtos!$P$69)<0.01,"",Produtos!$O$69)
A83: =IF(ABS(Produtos!$P$70)<0.01,"",Produtos!$B$70) | B83: =IF(ABS(Produtos!$P$70)<0.01,"",Produtos!$K$70) | C83: =IF(ABS(Produtos!$P$70)<0.01,"",Produtos!$O$70)
A84: =IF(ABS(Produtos!$P$71)<0.01,"",Produtos!$B$71) | B84: =IF(ABS(Produtos!$P$71)<0.01,"",Produtos!$K$71) | C84: =IF(ABS(Produtos!$P$71)<0.01,"",Produtos!$O$71)
A85: =IF(ABS(Produtos!$P$72)<0.01,"",Produtos!$B$72) -> Sanduba Veg | B85: =IF(ABS(Produtos!$P$72)<0.01,"",Produtos!$K$72) -> 1.7344443 | C85: =IF(ABS(Produtos!$P$72)<0.01,"",Produtos!$O$72) -> 0.7863
A86: =IF(ABS(Produtos!$P$73)<0.01,"",Produtos!$B$73) | B86: =IF(ABS(Produtos!$P$73)<0.01,"",Produtos!$K$73) | C86: =IF(ABS(Produtos!$P$73)<0.01,"",Produtos!$O$73)
A87: =IF(ABS(Produtos!$P$74)<0.01,"",Produtos!$B$74) | B87: =IF(ABS(Produtos!$P$74)<0.01,"",Produtos!$K$74) | C87: =IF(ABS(Produtos!$P$74)<0.01,"",Produtos!$O$74)
A88: =IF(ABS(Produtos!$P$75)<0.01,"",Produtos!$B$75) | B88: =IF(ABS(Produtos!$P$75)<0.01,"",Produtos!$K$75) | C88: =IF(ABS(Produtos!$P$75)<0.01,"",Produtos!$O$75)
A89: =IF(ABS(Produtos!$P$76)<0.01,"",Produtos!$B$76) -> Torta de Frango sem Ovos | B89: =IF(ABS(Produtos!$P$76)<0.01,"",Produtos!$K$76) -> 1.2071257 | C89: =IF(ABS(Produtos!$P$76)<0.01,"",Produtos!$O$76) -> 1.1916

Sheet Pendências
A1: Para você conferir
A2: Coisas que a planilha antiga deixava em aberto e que ninguém consegue adivinhar por você. Nada aqui impede de usar a planilha; é a lista do que vale olhar com calma.
A3: # | B3: O que encontramos
A4: 1 | B4: Pão-para Sanduiche: comprado por unidade. Falta saber quanto pesa uma unidade para o custo por quilo fechar.
A5: 2 | B5: Massa de Pizza Vegana: comprado por unidade. Falta saber quanto pesa uma unidade para o custo por quilo fechar.
A6: 3 | B6: Pão Funcional Levissima P 1 Sanduiche: comprado por unidade. Falta saber quanto pesa uma unidade para o custo por quilo fechar.
A7: 4 | B7: Probiotico: comprado por unidade. Falta saber quanto pesa uma unidade para o custo por quilo fechar.
A8: 5 | B8: A aba se chama 'PATINHO ACEBOLADO DE VEGETAIS A' mas por dentro está escrito 'PATINHO ACEBOLADO COM VEGETAIS ASSADOS'. Usamos o nome de dentro. Confirmar qual é o certo.
A9: 6 | B9: Frango com Chuchu e Molho Branc: o ingrediente 'ARROZ INTEGRAL COZIDO' não existe na lista de insumos e ficou de fora do custo.
A10: 7 | B10: A aba se chama 'FRANGO COM CHUCHU E MOLHO BRANC' mas por dentro está escrito 'FRANGO COM MOLHO CHUCHU E MOLHO BRANCO E ARROZ COM SEMENTES'. Usamos o nome de dentro. Confirmar qual é o certo.
A11: 8 | B11: A aba se chama 'SANDUBA DE FRANGO' mas por dentro está escrito 'SANDUBA DE PAO-NOBIS, FRANGO E REQUEIJU'. Usamos o nome de dentro. Confirmar qual é o certo.
A12: 9 | B12: A aba se chama 'ESCONDIDINHO DE FRANGO' mas por dentro está escrito 'ESCONDIDINHO DE CARNE'. Usamos o nome de dentro. Confirmar qual é o certo.
A13: 10 | B13: A aba se chama 'COXINHA de batata doce' mas por dentro está escrito 'COXINHA MASSA TRAD'. Usamos o nome de dentro. Confirmar qual é o certo.
A14: 11 | B14: A aba se chama 'CREME DE CASTANHA' mas por dentro está escrito 'CATUPIRY DE CASTANHA'. Usamos o nome de dentro. Confirmar qual é o certo.
A15: 12 | B15: A aba se chama 'PÃO CASEIRO' mas por dentro está escrito 'PÃO ROBERTA'. Usamos o nome de dentro. Confirmar qual é o certo.
... A49: 46 | B49: A aba se chama 'FRANGO DESFIADO COM MOLHO DE TO' mas por dentro está escrito 'FRANGO DESFIADO COM MOLHO DE TOMATE'. Usamos o nome de dentro. Confirmar qual é o certo.

Sheet Listas
A1: Listas
A2: Alimentam as caixinhas de escolha das outras abas.
A3: Categorias | B3: Unidades | C3: Fornecedores | D3: Vende?
A4: Bebidas | B4: kg | C4: Ademir | D4: Sim
A5: Caldos | B5: L | C5: Ares | D5: Não
A6: Massas e bases | B6: un | C6: Ares da Natureza
A7: Outros | C7: Argentina
A8: Pães | C8: Cacau Show
A9: Salgados assados | C9: Cantina
A10: Salgados fritos | C10: Cantina da Fruta
A11: Sanduíches | C11: Cedro
C12: Cipra
C13: Cometa
C14: Equi
C15: Equilibrium
C16: Farmacia
C17: Feirinha
C18: Fruteira
C19: Ingredientes Online
C20: Marcon Atacado Beltrao
C21: Marcon Atadaco Beltrao
C22: Melo
C23: Mercado Livre
... C29: cozinha
